<?xml version="1.0" encoding="utf-8"?>
<MasterAnimationList>
  <!--Warning: Generated by Kobol - changes to this file may be overwritten-->
  <_TableList>
    <RECORD>
      <Name TYPE="STR">Animations</Name>
    </RECORD>
    <RECORD>
      <Name TYPE="STR">SkeletonMovement</Name>
    </RECORD>
  </_TableList>
  <Animations>
    <RECORD>
      <AnimType KEY="TRUE" TYPE="STR">Appearance</AnimType>
      <NumAnims TYPE="INT">1</NumAnims>
      <Animation0 TYPE="UINT">205</Animation0>
    </RECORD>
    <RECORD>
      <AnimType KEY="TRUE" TYPE="STR">Attack</AnimType>
      <NumAnims TYPE="INT">1</NumAnims>
      <Animation0 TYPE="UINT">700</Animation0>
    </RECORD>
    <RECORD>
      <AnimType KEY="TRUE" TYPE="STR">Attack_Boy</AnimType>
      <NumAnims TYPE="INT">1</NumAnims>
      <Animation0 TYPE="UINT">700</Animation0>
    </RECORD>
    <RECORD>
      <AnimType KEY="TRUE" TYPE="STR">Attack_Boy_Banner</AnimType>
      <NumAnims TYPE="INT">1</NumAnims>
      <Animation0 TYPE="UINT">41700</Animation0>
    </RECORD>
    <RECORD>
      <AnimType KEY="TRUE" TYPE="STR">Attack_Boy_Bow</AnimType>
      <NumAnims TYPE="INT">1</NumAnims>
      <Animation0 TYPE="UINT">35700</Animation0>
    </RECORD>
    <RECORD>
      <AnimType KEY="TRUE" TYPE="STR">Attack_Boy_Crossbow</AnimType>
      <NumAnims TYPE="INT">1</NumAnims>
      <Animation0 TYPE="UINT">53700</Animation0>
    </RECORD>
    <RECORD>
      <AnimType KEY="TRUE" TYPE="STR">Attack_Boy_Lute</AnimType>
      <NumAnims TYPE="INT">1</NumAnims>
      <Animation0 TYPE="UINT">39700</Animation0>
    </RECORD>
    <RECORD>
      <AnimType KEY="TRUE" TYPE="STR">Attack_Boy_Relic</AnimType>
      <NumAnims TYPE="INT">1</NumAnims>
      <Animation0 TYPE="UINT">45700</Animation0>
    </RECORD>
    <RECORD>
      <AnimType KEY="TRUE" TYPE="STR">Attack_Boy_Rifle</AnimType>
      <NumAnims TYPE="INT">1</NumAnims>
      <Animation0 TYPE="UINT">50700</Animation0>
    </RECORD>
    <RECORD>
      <AnimType KEY="TRUE" TYPE="STR">Attack_Boy_Rifle_B</AnimType>
      <NumAnims TYPE="INT">1</NumAnims>
      <Animation0 TYPE="UINT">60700</Animation0>
    </RECORD>
    <RECORD>
      <AnimType KEY="TRUE" TYPE="STR">Attack_Boy_Spear</AnimType>
      <NumAnims TYPE="INT">1</NumAnims>
      <Animation0 TYPE="UINT">37700</Animation0>
    </RECORD>
    <RECORD>
      <AnimType KEY="TRUE" TYPE="STR">Attack_Boy_Sword_TwoHanded</AnimType>
      <NumAnims TYPE="INT">1</NumAnims>
      <Animation0 TYPE="UINT">24700</Animation0>
    </RECORD>
    <RECORD>
      <AnimType KEY="TRUE" TYPE="STR">Attack_Boy_SwordShield</AnimType>
      <NumAnims TYPE="INT">1</NumAnims>
      <Animation0 TYPE="UINT">43700</Animation0>
    </RECORD>
    <RECORD>
      <AnimType KEY="TRUE" TYPE="STR">Attack_Boy_Throw</AnimType>
      <NumAnims TYPE="INT">1</NumAnims>
      <Animation0 TYPE="UINT">54700</Animation0>
    </RECORD>
    <RECORD>
      <AnimType KEY="TRUE" TYPE="STR">Attack_Boy_Whip</AnimType>
      <NumAnims TYPE="INT">1</NumAnims>
      <Animation0 TYPE="UINT">56700</Animation0>
    </RECORD>
    <RECORD>
      <AnimType KEY="TRUE" TYPE="STR">Attack_Girl</AnimType>
      <NumAnims TYPE="INT">1</NumAnims>
      <Animation0 TYPE="UINT">700</Animation0>
    </RECORD>
    <RECORD>
      <AnimType KEY="TRUE" TYPE="STR">Attack_Girl_Relic</AnimType>
      <NumAnims TYPE="INT">1</NumAnims>
      <Animation0 TYPE="UINT">45700</Animation0>
    </RECORD>
    <RECORD>
      <AnimType KEY="TRUE" TYPE="STR">Attack_Girl_Sword_TwoHanded</AnimType>
      <NumAnims TYPE="INT">1</NumAnims>
      <Animation0 TYPE="UINT">25700</Animation0>
    </RECORD>
    <RECORD>
      <AnimType KEY="TRUE" TYPE="STR">Attack2</AnimType>
      <NumAnims TYPE="INT">1</NumAnims>
      <Animation0 TYPE="UINT">710</Animation0>
    </RECORD>
    <RECORD>
      <AnimType KEY="TRUE" TYPE="STR">Attack3</AnimType>
      <NumAnims TYPE="INT">1</NumAnims>
      <Animation0 TYPE="UINT">720</Animation0>
    </RECORD>
    <RECORD>
      <AnimType KEY="TRUE" TYPE="STR">Attack4</AnimType>
      <NumAnims TYPE="INT">1</NumAnims>
      <Animation0 TYPE="UINT">730</Animation0>
    </RECORD>
    <RECORD>
      <AnimType KEY="TRUE" TYPE="STR">Attack5</AnimType>
      <NumAnims TYPE="INT">1</NumAnims>
      <Animation0 TYPE="UINT">740</Animation0>
    </RECORD>
    <RECORD>
      <AnimType KEY="TRUE" TYPE="STR">BeanDance</AnimType>
      <NumAnims TYPE="INT">1</NumAnims>
      <Animation0 TYPE="UINT">585</Animation0>
    </RECORD>
    <RECORD>
      <AnimType KEY="TRUE" TYPE="STR">BeeDance</AnimType>
      <NumAnims TYPE="INT">1</NumAnims>
      <Animation0 TYPE="UINT">599</Animation0>
    </RECORD>
    <RECORD>
      <AnimType KEY="TRUE" TYPE="STR">Beg</AnimType>
      <NumAnims TYPE="INT">1</NumAnims>
      <Animation0 TYPE="UINT">601</Animation0>
    </RECORD>
    <RECORD>
      <AnimType KEY="TRUE" TYPE="STR">BernieDance</AnimType>
      <NumAnims TYPE="INT">1</NumAnims>
      <Animation0 TYPE="UINT">588</Animation0>
    </RECORD>
    <RECORD>
      <AnimType KEY="TRUE" TYPE="STR">Bow</AnimType>
      <NumAnims TYPE="INT">1</NumAnims>
      <Animation0 TYPE="UINT">602</Animation0>
    </RECORD>
    <RECORD>
      <AnimType KEY="TRUE" TYPE="STR">BreakinDance</AnimType>
      <NumAnims TYPE="INT">1</NumAnims>
      <Animation0 TYPE="UINT">594</Animation0>
    </RECORD>
    <RECORD>
      <AnimType KEY="TRUE" TYPE="STR">BrooklynDance</AnimType>
      <NumAnims TYPE="INT">1</NumAnims>
      <Animation0 TYPE="UINT">593</Animation0>
    </RECORD>
    <RECORD>
      <AnimType KEY="TRUE" TYPE="STR">Cast</AnimType>
      <NumAnims TYPE="INT">1</NumAnims>
      <Animation0 TYPE="UINT">144</Animation0>
    </RECORD>
    <RECORD>
      <AnimType KEY="TRUE" TYPE="STR">Cast_Boy</AnimType>
      <NumAnims TYPE="INT">1</NumAnims>
      <Animation0 TYPE="UINT">6144</Animation0>
    </RECORD>
    <RECORD>
      <AnimType KEY="TRUE" TYPE="STR">Cast_Boy_Banner</AnimType>
      <NumAnims TYPE="INT">1</NumAnims>
      <Animation0 TYPE="UINT">41144</Animation0>
    </RECORD>
    <RECORD>
      <AnimType KEY="TRUE" TYPE="STR">Cast_Boy_Bow</AnimType>
      <NumAnims TYPE="INT">1</NumAnims>
      <Animation0 TYPE="UINT">35144</Animation0>
    </RECORD>
    <RECORD>
      <AnimType KEY="TRUE" TYPE="STR">Cast_Boy_Flute</AnimType>
      <NumAnims TYPE="INT">1</NumAnims>
      <Animation0 TYPE="UINT">8144</Animation0>
    </RECORD>
    <RECORD>
      <AnimType KEY="TRUE" TYPE="STR">Cast_Boy_Lute</AnimType>
      <NumAnims TYPE="INT">1</NumAnims>
      <Animation0 TYPE="UINT">39144</Animation0>
    </RECORD>
    <RECORD>
      <AnimType KEY="TRUE" TYPE="STR">Cast_Boy_Relic</AnimType>
      <NumAnims TYPE="INT">1</NumAnims>
      <Animation0 TYPE="UINT">45144</Animation0>
    </RECORD>
    <RECORD>
      <AnimType KEY="TRUE" TYPE="STR">Cast_Boy_Rifle</AnimType>
      <NumAnims TYPE="INT">1</NumAnims>
      <Animation0 TYPE="UINT">50144</Animation0>
    </RECORD>
    <RECORD>
      <AnimType KEY="TRUE" TYPE="STR">Cast_Boy_Spear</AnimType>
      <NumAnims TYPE="INT">1</NumAnims>
      <Animation0 TYPE="UINT">37144</Animation0>
    </RECORD>
    <RECORD>
      <AnimType KEY="TRUE" TYPE="STR">Cast_Boy_Staff</AnimType>
      <NumAnims TYPE="INT">1</NumAnims>
      <Animation0 TYPE="UINT">144</Animation0>
    </RECORD>
    <RECORD>
      <AnimType KEY="TRUE" TYPE="STR">Cast_Boy_Sword</AnimType>
      <NumAnims TYPE="INT">1</NumAnims>
      <Animation0 TYPE="UINT">2144</Animation0>
    </RECORD>
    <RECORD>
      <AnimType KEY="TRUE" TYPE="STR">Cast_Boy_Sword_TwoHanded</AnimType>
      <NumAnims TYPE="INT">1</NumAnims>
      <Animation0 TYPE="UINT">24144</Animation0>
    </RECORD>
    <RECORD>
      <AnimType KEY="TRUE" TYPE="STR">Cast_Boy_SwordShield</AnimType>
      <NumAnims TYPE="INT">1</NumAnims>
      <Animation0 TYPE="UINT">43144</Animation0>
    </RECORD>
    <RECORD>
      <AnimType KEY="TRUE" TYPE="STR">Cast_Boy_Throw</AnimType>
      <NumAnims TYPE="INT">1</NumAnims>
      <Animation0 TYPE="UINT">54144</Animation0>
    </RECORD>
    <RECORD>
      <AnimType KEY="TRUE" TYPE="STR">Cast_Boy_Wand</AnimType>
      <NumAnims TYPE="INT">1</NumAnims>
      <Animation0 TYPE="UINT">2144</Animation0>
    </RECORD>
    <RECORD>
      <AnimType KEY="TRUE" TYPE="STR">Cast_Boy_Whip</AnimType>
      <NumAnims TYPE="INT">1</NumAnims>
      <Animation0 TYPE="UINT">56144</Animation0>
    </RECORD>
    <RECORD>
      <AnimType KEY="TRUE" TYPE="STR">Cast_Girl</AnimType>
      <NumAnims TYPE="INT">1</NumAnims>
      <Animation0 TYPE="UINT">6144</Animation0>
    </RECORD>
    <RECORD>
      <AnimType KEY="TRUE" TYPE="STR">Cast_Girl_Flute</AnimType>
      <NumAnims TYPE="INT">1</NumAnims>
      <Animation0 TYPE="UINT">8144</Animation0>
    </RECORD>
    <RECORD>
      <AnimType KEY="TRUE" TYPE="STR">Cast_Girl_Relic</AnimType>
      <NumAnims TYPE="INT">1</NumAnims>
      <Animation0 TYPE="UINT">45144</Animation0>
    </RECORD>
    <RECORD>
      <AnimType KEY="TRUE" TYPE="STR">Cast_Girl_Staff</AnimType>
      <NumAnims TYPE="INT">1</NumAnims>
      <Animation0 TYPE="UINT">144</Animation0>
    </RECORD>
    <RECORD>
      <AnimType KEY="TRUE" TYPE="STR">Cast_Girl_Sword</AnimType>
      <NumAnims TYPE="INT">1</NumAnims>
      <Animation0 TYPE="UINT">2144</Animation0>
    </RECORD>
    <RECORD>
      <AnimType KEY="TRUE" TYPE="STR">Cast_Girl_Sword_TwoHanded</AnimType>
      <NumAnims TYPE="INT">1</NumAnims>
      <Animation0 TYPE="UINT">25144</Animation0>
    </RECORD>
    <RECORD>
      <AnimType KEY="TRUE" TYPE="STR">Cast_Girl_Wand</AnimType>
      <NumAnims TYPE="INT">1</NumAnims>
      <Animation0 TYPE="UINT">2144</Animation0>
    </RECORD>
    <RECORD>
      <AnimType KEY="TRUE" TYPE="STR">Cast_Lute_MetalPumpkin</AnimType>
      <NumAnims TYPE="INT">1</NumAnims>
      <Animation0 TYPE="UINT">39146</Animation0>
    </RECORD>
    <RECORD>
      <AnimType KEY="TRUE" TYPE="STR">Cast_Lute_MetalSkull</AnimType>
      <NumAnims TYPE="INT">1</NumAnims>
      <Animation0 TYPE="UINT">39147</Animation0>
    </RECORD>
    <RECORD>
      <AnimType KEY="TRUE" TYPE="STR">Chat</AnimType>
      <NumAnims TYPE="INT">1</NumAnims>
      <Animation0 TYPE="UINT">614</Animation0>
    </RECORD>
    <RECORD>
      <AnimType KEY="TRUE" TYPE="STR">Cheer</AnimType>
      <NumAnims TYPE="INT">1</NumAnims>
      <Animation0 TYPE="UINT">603</Animation0>
    </RECORD>
    <RECORD>
      <AnimType KEY="TRUE" TYPE="STR">ChickenDance</AnimType>
      <NumAnims TYPE="INT">1</NumAnims>
      <Animation0 TYPE="UINT">623</Animation0>
    </RECORD>
    <RECORD>
      <AnimType KEY="TRUE" TYPE="STR">Clap</AnimType>
      <NumAnims TYPE="INT">1</NumAnims>
      <Animation0 TYPE="UINT">604</Animation0>
    </RECORD>
    <RECORD>
      <AnimType KEY="TRUE" TYPE="STR">CombatIdle</AnimType>
      <NumAnims TYPE="INT">1</NumAnims>
      <Animation0 TYPE="UINT">1</Animation0>
    </RECORD>
    <RECORD>
      <AnimType KEY="TRUE" TYPE="STR">CombatIdle_Boy_Bow</AnimType>
      <NumAnims TYPE="INT">1</NumAnims>
      <Animation0 TYPE="UINT">35001</Animation0>
    </RECORD>
    <RECORD>
      <AnimType KEY="TRUE" TYPE="STR">CombatIdle_Boy_Relic</AnimType>
      <NumAnims TYPE="INT">1</NumAnims>
      <Animation0 TYPE="UINT">45001</Animation0>
    </RECORD>
    <RECORD>
      <AnimType KEY="TRUE" TYPE="STR">CombatIdle_Boy_Rifle</AnimType>
      <NumAnims TYPE="INT">1</NumAnims>
      <Animation0 TYPE="UINT">50001</Animation0>
    </RECORD>
    <RECORD>
      <AnimType KEY="TRUE" TYPE="STR">CombatIdle_Boy_SwordShield</AnimType>
      <NumAnims TYPE="INT">1</NumAnims>
      <Animation0 TYPE="UINT">43001</Animation0>
    </RECORD>
    <RECORD>
      <AnimType KEY="TRUE" TYPE="STR">CombatIdle_Boy_Whip</AnimType>
      <NumAnims TYPE="INT">1</NumAnims>
      <Animation0 TYPE="UINT">56001</Animation0>
    </RECORD>
    <RECORD>
      <AnimType KEY="TRUE" TYPE="STR">CombatIdle_Girl_Relic</AnimType>
      <NumAnims TYPE="INT">1</NumAnims>
      <Animation0 TYPE="UINT">45001</Animation0>
    </RECORD>
    <RECORD>
      <AnimType KEY="TRUE" TYPE="STR">CombatIdleFidget</AnimType>
      <NumAnims TYPE="INT">1</NumAnims>
      <Animation0 TYPE="UINT">10</Animation0>
    </RECORD>
    <RECORD>
      <AnimType KEY="TRUE" TYPE="STR">Cry</AnimType>
      <NumAnims TYPE="INT">1</NumAnims>
      <Animation0 TYPE="UINT">605</Animation0>
    </RECORD>
    <RECORD>
      <AnimType KEY="TRUE" TYPE="STR">DabDance</AnimType>
      <NumAnims TYPE="INT">1</NumAnims>
      <Animation0 TYPE="UINT">297</Animation0>
    </RECORD>
    <RECORD>
      <AnimType KEY="TRUE" TYPE="STR">Dance</AnimType>
      <NumAnims TYPE="INT">1</NumAnims>
      <Animation0 TYPE="UINT">600</Animation0>
    </RECORD>
    <RECORD>
      <AnimType KEY="TRUE" TYPE="STR">Dance_BigDogg</AnimType>
      <NumAnims TYPE="INT">1</NumAnims>
      <Animation0 TYPE="UINT">645</Animation0>
    </RECORD>
    <RECORD>
      <AnimType KEY="TRUE" TYPE="STR">DanceFail</AnimType>
      <NumAnims TYPE="INT">1</NumAnims>
      <Animation0 TYPE="UINT">680</Animation0>
    </RECORD>
    <RECORD>
      <AnimType KEY="TRUE" TYPE="STR">Death</AnimType>
      <NumAnims TYPE="INT">1</NumAnims>
      <Animation0 TYPE="UINT">610</Animation0>
    </RECORD>
    <RECORD>
      <AnimType KEY="TRUE" TYPE="STR">Death_Boy_Relic</AnimType>
      <NumAnims TYPE="INT">1</NumAnims>
      <Animation0 TYPE="UINT">45610</Animation0>
    </RECORD>
    <RECORD>
      <AnimType KEY="TRUE" TYPE="STR">Death_Girl_Relic</AnimType>
      <NumAnims TYPE="INT">1</NumAnims>
      <Animation0 TYPE="UINT">45610</Animation0>
    </RECORD>
    <RECORD>
      <AnimType KEY="TRUE" TYPE="STR">Dialogue_03</AnimType>
      <NumAnims TYPE="INT">1</NumAnims>
      <Animation0 TYPE="UINT">62</Animation0>
    </RECORD>
    <RECORD>
      <AnimType KEY="TRUE" TYPE="STR">Disappear</AnimType>
      <NumAnims TYPE="INT">1</NumAnims>
      <Animation0 TYPE="UINT">2</Animation0>
    </RECORD>
    <RECORD>
      <AnimType KEY="TRUE" TYPE="STR">Dying</AnimType>
      <NumAnims TYPE="INT">1</NumAnims>
      <Animation0 TYPE="UINT">615</Animation0>
    </RECORD>
    <RECORD>
      <AnimType KEY="TRUE" TYPE="STR">ElaineDance</AnimType>
      <NumAnims TYPE="INT">1</NumAnims>
      <Animation0 TYPE="UINT">591</Animation0>
    </RECORD>
    <RECORD>
      <AnimType KEY="TRUE" TYPE="STR">FancyFeetDance</AnimType>
      <NumAnims TYPE="INT">1</NumAnims>
      <Animation0 TYPE="UINT">298</Animation0>
    </RECORD>
    <RECORD>
      <AnimType KEY="TRUE" TYPE="STR">Fidget_Boy_Swim_SwordShield</AnimType>
      <NumAnims TYPE="INT">1</NumAnims>
      <Animation0 TYPE="UINT">43032</Animation0>
    </RECORD>
    <RECORD>
      <AnimType KEY="TRUE" TYPE="STR">Fidget_Boy_SwordShield</AnimType>
      <NumAnims TYPE="INT">1</NumAnims>
      <Animation0 TYPE="UINT">43030</Animation0>
    </RECORD>
    <RECORD>
      <AnimType KEY="TRUE" TYPE="STR">Flex</AnimType>
      <NumAnims TYPE="INT">1</NumAnims>
      <Animation0 TYPE="UINT">606</Animation0>
    </RECORD>
    <RECORD>
      <AnimType KEY="TRUE" TYPE="STR">FlossDance</AnimType>
      <NumAnims TYPE="INT">1</NumAnims>
      <Animation0 TYPE="UINT">592</Animation0>
    </RECORD>
    <RECORD>
      <AnimType KEY="TRUE" TYPE="STR">FlyAway</AnimType>
      <NumAnims TYPE="INT">1</NumAnims>
      <Animation0 TYPE="UINT">3</Animation0>
    </RECORD>
    <RECORD>
      <AnimType KEY="TRUE" TYPE="STR">Focus</AnimType>
      <NumAnims TYPE="INT">1</NumAnims>
      <Animation0 TYPE="UINT">100</Animation0>
    </RECORD>
    <RECORD>
      <AnimType KEY="TRUE" TYPE="STR">Focus_Boy</AnimType>
      <NumAnims TYPE="INT">1</NumAnims>
      <Animation0 TYPE="UINT">6100</Animation0>
    </RECORD>
    <RECORD>
      <AnimType KEY="TRUE" TYPE="STR">Focus_Boy_Staff</AnimType>
      <NumAnims TYPE="INT">1</NumAnims>
      <Animation0 TYPE="UINT">100</Animation0>
    </RECORD>
    <RECORD>
      <AnimType KEY="TRUE" TYPE="STR">Focus_Boy_Sword</AnimType>
      <NumAnims TYPE="INT">1</NumAnims>
      <Animation0 TYPE="UINT">2100</Animation0>
    </RECORD>
    <RECORD>
      <AnimType KEY="TRUE" TYPE="STR">Focus_Boy_Sword_TwoHanded</AnimType>
      <NumAnims TYPE="INT">1</NumAnims>
      <Animation0 TYPE="UINT">24100</Animation0>
    </RECORD>
    <RECORD>
      <AnimType KEY="TRUE" TYPE="STR">Focus_Boy_Wand</AnimType>
      <NumAnims TYPE="INT">1</NumAnims>
      <Animation0 TYPE="UINT">2100</Animation0>
    </RECORD>
    <RECORD>
      <AnimType KEY="TRUE" TYPE="STR">Focus_Girl</AnimType>
      <NumAnims TYPE="INT">1</NumAnims>
      <Animation0 TYPE="UINT">6100</Animation0>
    </RECORD>
    <RECORD>
      <AnimType KEY="TRUE" TYPE="STR">Focus_Girl_Staff</AnimType>
      <NumAnims TYPE="INT">1</NumAnims>
      <Animation0 TYPE="UINT">100</Animation0>
    </RECORD>
    <RECORD>
      <AnimType KEY="TRUE" TYPE="STR">Focus_Girl_Sword</AnimType>
      <NumAnims TYPE="INT">1</NumAnims>
      <Animation0 TYPE="UINT">2100</Animation0>
    </RECORD>
    <RECORD>
      <AnimType KEY="TRUE" TYPE="STR">Focus_Girl_Sword_TwoHanded</AnimType>
      <NumAnims TYPE="INT">1</NumAnims>
      <Animation0 TYPE="UINT">24100</Animation0>
    </RECORD>
    <RECORD>
      <AnimType KEY="TRUE" TYPE="STR">Focus_Girl_Wand</AnimType>
      <NumAnims TYPE="INT">1</NumAnims>
      <Animation0 TYPE="UINT">2100</Animation0>
    </RECORD>
    <RECORD>
      <AnimType KEY="TRUE" TYPE="STR">Follow_Boy</AnimType>
      <NumAnims TYPE="INT">1</NumAnims>
      <Animation0 TYPE="UINT">501</Animation0>
    </RECORD>
    <RECORD>
      <AnimType KEY="TRUE" TYPE="STR">Fresh</AnimType>
      <NumAnims TYPE="INT">1</NumAnims>
      <Animation0 TYPE="UINT">598</Animation0>
    </RECORD>
    <RECORD>
      <AnimType KEY="TRUE" TYPE="STR">Funky</AnimType>
      <NumAnims TYPE="INT">1</NumAnims>
      <Animation0 TYPE="UINT">596</Animation0>
    </RECORD>
    <RECORD>
      <AnimType KEY="TRUE" TYPE="STR">FunkyChickenDance</AnimType>
      <NumAnims TYPE="INT">1</NumAnims>
      <Animation0 TYPE="UINT">590</Animation0>
    </RECORD>
    <RECORD>
      <AnimType KEY="TRUE" TYPE="STR">Gen_Dial_01</AnimType>
      <NumAnims TYPE="INT">1</NumAnims>
      <Animation0 TYPE="UINT">60</Animation0>
    </RECORD>
    <RECORD>
      <AnimType KEY="TRUE" TYPE="STR">Gen_Dial_02</AnimType>
      <NumAnims TYPE="INT">1</NumAnims>
      <Animation0 TYPE="UINT">61</Animation0>
    </RECORD>
    <RECORD>
      <AnimType KEY="TRUE" TYPE="STR">Gen_Dial_03</AnimType>
      <NumAnims TYPE="INT">1</NumAnims>
      <Animation0 TYPE="UINT">62</Animation0>
    </RECORD>
    <RECORD>
      <AnimType KEY="TRUE" TYPE="STR">Gen_Dial_04</AnimType>
      <NumAnims TYPE="INT">1</NumAnims>
      <Animation0 TYPE="UINT">63</Animation0>
    </RECORD>
    <RECORD>
      <AnimType KEY="TRUE" TYPE="STR">Gen_Dial_05</AnimType>
      <NumAnims TYPE="INT">1</NumAnims>
      <Animation0 TYPE="UINT">64</Animation0>
    </RECORD>
    <RECORD>
      <AnimType KEY="TRUE" TYPE="STR">Gen_Dial_06</AnimType>
      <NumAnims TYPE="INT">1</NumAnims>
      <Animation0 TYPE="UINT">65</Animation0>
    </RECORD>
    <RECORD>
      <AnimType KEY="TRUE" TYPE="STR">Gen_Dial_07</AnimType>
      <NumAnims TYPE="INT">1</NumAnims>
      <Animation0 TYPE="UINT">66</Animation0>
    </RECORD>
    <RECORD>
      <AnimType KEY="TRUE" TYPE="STR">Gen_Dial_08</AnimType>
      <NumAnims TYPE="INT">1</NumAnims>
      <Animation0 TYPE="UINT">67</Animation0>
    </RECORD>
    <RECORD>
      <AnimType KEY="TRUE" TYPE="STR">GetHit</AnimType>
      <NumAnims TYPE="INT">1</NumAnims>
      <Animation0 TYPE="UINT">370</Animation0>
    </RECORD>
    <RECORD>
      <AnimType KEY="TRUE" TYPE="STR">GetHit_Back</AnimType>
      <NumAnims TYPE="INT">1</NumAnims>
      <Animation0 TYPE="UINT">370</Animation0>
    </RECORD>
    <RECORD>
      <AnimType KEY="TRUE" TYPE="STR">GetHit_DarkSprite</AnimType>
      <NumAnims TYPE="INT">1</NumAnims>
      <Animation0 TYPE="UINT">376</Animation0>
    </RECORD>
    <RECORD>
      <AnimType KEY="TRUE" TYPE="STR">GetHit_DeathLv2-1</AnimType>
      <NumAnims TYPE="INT">1</NumAnims>
      <Animation0 TYPE="UINT">377</Animation0>
    </RECORD>
    <RECORD>
      <AnimType KEY="TRUE" TYPE="STR">GetHit_DeathLv2-2</AnimType>
      <NumAnims TYPE="INT">1</NumAnims>
      <Animation0 TYPE="UINT">378</Animation0>
    </RECORD>
    <RECORD>
      <AnimType KEY="TRUE" TYPE="STR">GetHit_DeathLv3-1</AnimType>
      <NumAnims TYPE="INT">1</NumAnims>
      <Animation0 TYPE="UINT">379</Animation0>
    </RECORD>
    <RECORD>
      <AnimType KEY="TRUE" TYPE="STR">GetHit_Dryad</AnimType>
      <NumAnims TYPE="INT">1</NumAnims>
      <Animation0 TYPE="UINT">380</Animation0>
    </RECORD>
    <RECORD>
      <AnimType KEY="TRUE" TYPE="STR">GetHit_FireLv3</AnimType>
      <NumAnims TYPE="INT">1</NumAnims>
      <Animation0 TYPE="UINT">381</Animation0>
    </RECORD>
    <RECORD>
      <AnimType KEY="TRUE" TYPE="STR">GetHit_FrostGiant</AnimType>
      <NumAnims TYPE="INT">1</NumAnims>
      <Animation0 TYPE="UINT">382</Animation0>
    </RECORD>
    <RECORD>
      <AnimType KEY="TRUE" TYPE="STR">GetHit_Ghost</AnimType>
      <NumAnims TYPE="INT">1</NumAnims>
      <Animation0 TYPE="UINT">383</Animation0>
    </RECORD>
    <RECORD>
      <AnimType KEY="TRUE" TYPE="STR">GetHit_Heal</AnimType>
      <NumAnims TYPE="INT">1</NumAnims>
      <Animation0 TYPE="UINT">371</Animation0>
    </RECORD>
    <RECORD>
      <AnimType KEY="TRUE" TYPE="STR">GetHit_HeckHound</AnimType>
      <NumAnims TYPE="INT">1</NumAnims>
      <Animation0 TYPE="UINT">384</Animation0>
    </RECORD>
    <RECORD>
      <AnimType KEY="TRUE" TYPE="STR">GetHit_Hellephant</AnimType>
      <NumAnims TYPE="INT">1</NumAnims>
      <Animation0 TYPE="UINT">385</Animation0>
    </RECORD>
    <RECORD>
      <AnimType KEY="TRUE" TYPE="STR">GetHit_HumungoFrog</AnimType>
      <NumAnims TYPE="INT">1</NumAnims>
      <Animation0 TYPE="UINT">386</Animation0>
    </RECORD>
    <RECORD>
      <AnimType KEY="TRUE" TYPE="STR">GetHit_Imp</AnimType>
      <NumAnims TYPE="INT">1</NumAnims>
      <Animation0 TYPE="UINT">387</Animation0>
    </RECORD>
    <RECORD>
      <AnimType KEY="TRUE" TYPE="STR">GetHit_Kraken</AnimType>
      <NumAnims TYPE="INT">1</NumAnims>
      <Animation0 TYPE="UINT">388</Animation0>
    </RECORD>
    <RECORD>
      <AnimType KEY="TRUE" TYPE="STR">GetHit_LifeHurt</AnimType>
      <NumAnims TYPE="INT">1</NumAnims>
      <Animation0 TYPE="UINT">369</Animation0>
    </RECORD>
    <RECORD>
      <AnimType KEY="TRUE" TYPE="STR">GetHit_LifeLv3</AnimType>
      <NumAnims TYPE="INT">1</NumAnims>
      <Animation0 TYPE="UINT">389</Animation0>
    </RECORD>
    <RECORD>
      <AnimType KEY="TRUE" TYPE="STR">GetHit_LightningBats</AnimType>
      <NumAnims TYPE="INT">1</NumAnims>
      <Animation0 TYPE="UINT">390</Animation0>
    </RECORD>
    <RECORD>
      <AnimType KEY="TRUE" TYPE="STR">GetHit_Phoenix</AnimType>
      <NumAnims TYPE="INT">1</NumAnims>
      <Animation0 TYPE="UINT">391</Animation0>
    </RECORD>
    <RECORD>
      <AnimType KEY="TRUE" TYPE="STR">GetHit_SnowSerpent</AnimType>
      <NumAnims TYPE="INT">1</NumAnims>
      <Animation0 TYPE="UINT">392</Animation0>
    </RECORD>
    <RECORD>
      <AnimType KEY="TRUE" TYPE="STR">GetHit_Spirit</AnimType>
      <NumAnims TYPE="INT">1</NumAnims>
      <Animation0 TYPE="UINT">398</Animation0>
    </RECORD>
    <RECORD>
      <AnimType KEY="TRUE" TYPE="STR">GetHit_Steal</AnimType>
      <NumAnims TYPE="INT">1</NumAnims>
      <Animation0 TYPE="UINT">393</Animation0>
    </RECORD>
    <RECORD>
      <AnimType KEY="TRUE" TYPE="STR">GetHit_StormLv2</AnimType>
      <NumAnims TYPE="INT">1</NumAnims>
      <Animation0 TYPE="UINT">394</Animation0>
    </RECORD>
    <RECORD>
      <AnimType KEY="TRUE" TYPE="STR">GetHit_StormLv3</AnimType>
      <NumAnims TYPE="INT">1</NumAnims>
      <Animation0 TYPE="UINT">395</Animation0>
    </RECORD>
    <RECORD>
      <AnimType KEY="TRUE" TYPE="STR">GetHit_StormShark</AnimType>
      <NumAnims TYPE="INT">1</NumAnims>
      <Animation0 TYPE="UINT">396</Animation0>
    </RECORD>
    <RECORD>
      <AnimType KEY="TRUE" TYPE="STR">GetHit_Up</AnimType>
      <NumAnims TYPE="INT">1</NumAnims>
      <Animation0 TYPE="UINT">372</Animation0>
    </RECORD>
    <RECORD>
      <AnimType KEY="TRUE" TYPE="STR">GetHit_Wyvern</AnimType>
      <NumAnims TYPE="INT">1</NumAnims>
      <Animation0 TYPE="UINT">397</Animation0>
    </RECORD>
    <RECORD>
      <AnimType KEY="TRUE" TYPE="STR">Idle</AnimType>
      <NumAnims TYPE="INT">1</NumAnims>
      <Animation0 TYPE="UINT">20</Animation0>
    </RECORD>
    <RECORD>
      <AnimType KEY="TRUE" TYPE="STR">Idle_Boy</AnimType>
      <NumAnims TYPE="INT">1</NumAnims>
      <Animation0 TYPE="UINT">6020</Animation0>
    </RECORD>
    <RECORD>
      <AnimType KEY="TRUE" TYPE="STR">Idle_Boy_Banner</AnimType>
      <NumAnims TYPE="INT">1</NumAnims>
      <Animation0 TYPE="UINT">41020</Animation0>
    </RECORD>
    <RECORD>
      <AnimType KEY="TRUE" TYPE="STR">Idle_Boy_Bow</AnimType>
      <NumAnims TYPE="INT">1</NumAnims>
      <Animation0 TYPE="UINT">35020</Animation0>
    </RECORD>
    <RECORD>
      <AnimType KEY="TRUE" TYPE="STR">Idle_Boy_Mask</AnimType>
      <NumAnims TYPE="INT">1</NumAnims>
      <Animation0 TYPE="UINT">58020</Animation0>
    </RECORD>
    <RECORD>
      <AnimType KEY="TRUE" TYPE="STR">Idle_Boy_Relic</AnimType>
      <NumAnims TYPE="INT">1</NumAnims>
      <Animation0 TYPE="UINT">45020</Animation0>
    </RECORD>
    <RECORD>
      <AnimType KEY="TRUE" TYPE="STR">Idle_Boy_Rifle</AnimType>
      <NumAnims TYPE="INT">1</NumAnims>
      <Animation0 TYPE="UINT">50020</Animation0>
    </RECORD>
    <RECORD>
      <AnimType KEY="TRUE" TYPE="STR">Idle_Boy_Spear</AnimType>
      <NumAnims TYPE="INT">1</NumAnims>
      <Animation0 TYPE="UINT">37020</Animation0>
    </RECORD>
    <RECORD>
      <AnimType KEY="TRUE" TYPE="STR">Idle_Boy_Staff</AnimType>
      <NumAnims TYPE="INT">1</NumAnims>
      <Animation0 TYPE="UINT">20</Animation0>
    </RECORD>
    <RECORD>
      <AnimType KEY="TRUE" TYPE="STR">Idle_Boy_Swim_SwordShield</AnimType>
      <NumAnims TYPE="INT">1</NumAnims>
      <Animation0 TYPE="UINT">43022</Animation0>
    </RECORD>
    <RECORD>
      <AnimType KEY="TRUE" TYPE="STR">Idle_Boy_Sword</AnimType>
      <NumAnims TYPE="INT">1</NumAnims>
      <Animation0 TYPE="UINT">2020</Animation0>
    </RECORD>
    <RECORD>
      <AnimType KEY="TRUE" TYPE="STR">Idle_Boy_Sword_TwoHanded</AnimType>
      <NumAnims TYPE="INT">1</NumAnims>
      <Animation0 TYPE="UINT">24020</Animation0>
    </RECORD>
    <RECORD>
      <AnimType KEY="TRUE" TYPE="STR">Idle_Boy_SwordShield</AnimType>
      <NumAnims TYPE="INT">1</NumAnims>
      <Animation0 TYPE="UINT">43020</Animation0>
    </RECORD>
    <RECORD>
      <AnimType KEY="TRUE" TYPE="STR">Idle_Boy_Throw</AnimType>
      <NumAnims TYPE="INT">1</NumAnims>
      <Animation0 TYPE="UINT">54020</Animation0>
    </RECORD>
    <RECORD>
      <AnimType KEY="TRUE" TYPE="STR">Idle_Boy_Wand</AnimType>
      <NumAnims TYPE="INT">1</NumAnims>
      <Animation0 TYPE="UINT">2020</Animation0>
    </RECORD>
    <RECORD>
      <AnimType KEY="TRUE" TYPE="STR">Idle_Boy_Whip</AnimType>
      <NumAnims TYPE="INT">1</NumAnims>
      <Animation0 TYPE="UINT">56020</Animation0>
    </RECORD>
    <RECORD>
      <AnimType KEY="TRUE" TYPE="STR">Idle_Fidget_Boy_Mask</AnimType>
      <NumAnims TYPE="INT">1</NumAnims>
      <Animation0 TYPE="UINT">58030</Animation0>
    </RECORD>
    <RECORD>
      <AnimType KEY="TRUE" TYPE="STR">Idle_Girl</AnimType>
      <NumAnims TYPE="INT">1</NumAnims>
      <Animation0 TYPE="UINT">7020</Animation0>
    </RECORD>
    <RECORD>
      <AnimType KEY="TRUE" TYPE="STR">Idle_Girl_Relic</AnimType>
      <NumAnims TYPE="INT">1</NumAnims>
      <Animation0 TYPE="UINT">46020</Animation0>
    </RECORD>
    <RECORD>
      <AnimType KEY="TRUE" TYPE="STR">Idle_Girl_Staff</AnimType>
      <NumAnims TYPE="INT">1</NumAnims>
      <Animation0 TYPE="UINT">1020</Animation0>
    </RECORD>
    <RECORD>
      <AnimType KEY="TRUE" TYPE="STR">Idle_Girl_Sword</AnimType>
      <NumAnims TYPE="INT">1</NumAnims>
      <Animation0 TYPE="UINT">3020</Animation0>
    </RECORD>
    <RECORD>
      <AnimType KEY="TRUE" TYPE="STR">Idle_Girl_Sword_TwoHanded</AnimType>
      <NumAnims TYPE="INT">1</NumAnims>
      <Animation0 TYPE="UINT">25020</Animation0>
    </RECORD>
    <RECORD>
      <AnimType KEY="TRUE" TYPE="STR">Idle_Girl_Throw</AnimType>
      <NumAnims TYPE="INT">1</NumAnims>
      <Animation0 TYPE="UINT">55020</Animation0>
    </RECORD>
    <RECORD>
      <AnimType KEY="TRUE" TYPE="STR">Idle_Girl_Wand</AnimType>
      <NumAnims TYPE="INT">1</NumAnims>
      <Animation0 TYPE="UINT">3020</Animation0>
    </RECORD>
    <RECORD>
      <AnimType KEY="TRUE" TYPE="STR">Idle2_Boy_Jump_Mask</AnimType>
      <NumAnims TYPE="INT">1</NumAnims>
      <Animation0 TYPE="UINT">58220</Animation0>
    </RECORD>
    <RECORD>
      <AnimType KEY="TRUE" TYPE="STR">IdleFidget</AnimType>
      <NumAnims TYPE="INT">1</NumAnims>
      <Animation0 TYPE="UINT">30</Animation0>
    </RECORD>
    <RECORD>
      <AnimType KEY="TRUE" TYPE="STR">IdleFidget_Boy</AnimType>
      <NumAnims TYPE="INT">1</NumAnims>
      <Animation0 TYPE="UINT">2030</Animation0>
    </RECORD>
    <RECORD>
      <AnimType KEY="TRUE" TYPE="STR">IdleFidget_Boy_Banner</AnimType>
      <NumAnims TYPE="INT">1</NumAnims>
      <Animation0 TYPE="UINT">41030</Animation0>
    </RECORD>
    <RECORD>
      <AnimType KEY="TRUE" TYPE="STR">IdleFidget_Boy_Bow</AnimType>
      <NumAnims TYPE="INT">1</NumAnims>
      <Animation0 TYPE="UINT">35030</Animation0>
    </RECORD>
    <RECORD>
      <AnimType KEY="TRUE" TYPE="STR">IdleFidget_Boy_Lute</AnimType>
      <NumAnims TYPE="INT">1</NumAnims>
      <Animation0 TYPE="UINT">39030</Animation0>
    </RECORD>
    <RECORD>
      <AnimType KEY="TRUE" TYPE="STR">IdleFidget_Boy_Relic</AnimType>
      <NumAnims TYPE="INT">1</NumAnims>
      <Animation0 TYPE="UINT">45030</Animation0>
    </RECORD>
    <RECORD>
      <AnimType KEY="TRUE" TYPE="STR">IdleFidget_Boy_Rifle</AnimType>
      <NumAnims TYPE="INT">1</NumAnims>
      <Animation0 TYPE="UINT">50030</Animation0>
    </RECORD>
    <RECORD>
      <AnimType KEY="TRUE" TYPE="STR">IdleFidget_Boy_Spear</AnimType>
      <NumAnims TYPE="INT">1</NumAnims>
      <Animation0 TYPE="UINT">37030</Animation0>
    </RECORD>
    <RECORD>
      <AnimType KEY="TRUE" TYPE="STR">IdleFidget_Boy_Staff</AnimType>
      <NumAnims TYPE="INT">2</NumAnims>
      <Animation0 TYPE="UINT">30</Animation0>
      <Animation1 TYPE="UINT">31</Animation1>
    </RECORD>
    <RECORD>
      <AnimType KEY="TRUE" TYPE="STR">IdleFidget_Boy_Sword</AnimType>
      <NumAnims TYPE="INT">1</NumAnims>
      <Animation0 TYPE="UINT">2030</Animation0>
    </RECORD>
    <RECORD>
      <AnimType KEY="TRUE" TYPE="STR">IdleFidget_Boy_Sword_TwoHanded</AnimType>
      <NumAnims TYPE="INT">1</NumAnims>
      <Animation0 TYPE="UINT">24030</Animation0>
    </RECORD>
    <RECORD>
      <AnimType KEY="TRUE" TYPE="STR">IdleFidget_Boy_Wand</AnimType>
      <NumAnims TYPE="INT">1</NumAnims>
      <Animation0 TYPE="UINT">2030</Animation0>
    </RECORD>
    <RECORD>
      <AnimType KEY="TRUE" TYPE="STR">IdleFidget_Boy_Whip</AnimType>
      <NumAnims TYPE="INT">1</NumAnims>
      <Animation0 TYPE="UINT">56030</Animation0>
    </RECORD>
    <RECORD>
      <AnimType KEY="TRUE" TYPE="STR">IdleFidget_Girl</AnimType>
      <NumAnims TYPE="INT">1</NumAnims>
      <Animation0 TYPE="UINT">3030</Animation0>
    </RECORD>
    <RECORD>
      <AnimType KEY="TRUE" TYPE="STR">IdleFidget_Girl_Lute</AnimType>
      <NumAnims TYPE="INT">1</NumAnims>
      <Animation0 TYPE="UINT">40030</Animation0>
    </RECORD>
    <RECORD>
      <AnimType KEY="TRUE" TYPE="STR">IdleFidget_Girl_Relic</AnimType>
      <NumAnims TYPE="INT">1</NumAnims>
      <Animation0 TYPE="UINT">45030</Animation0>
    </RECORD>
    <RECORD>
      <AnimType KEY="TRUE" TYPE="STR">IdleFidget_Girl_Staff</AnimType>
      <NumAnims TYPE="INT">1</NumAnims>
      <Animation0 TYPE="UINT">1030</Animation0>
    </RECORD>
    <RECORD>
      <AnimType KEY="TRUE" TYPE="STR">IdleFidget_Girl_Sword</AnimType>
      <NumAnims TYPE="INT">1</NumAnims>
      <Animation0 TYPE="UINT">3030</Animation0>
    </RECORD>
    <RECORD>
      <AnimType KEY="TRUE" TYPE="STR">IdleFidget_Girl_Sword_TwoHanded</AnimType>
      <NumAnims TYPE="INT">1</NumAnims>
      <Animation0 TYPE="UINT">25030</Animation0>
    </RECORD>
    <RECORD>
      <AnimType KEY="TRUE" TYPE="STR">IdleFidget_Girl_Throw</AnimType>
      <NumAnims TYPE="INT">1</NumAnims>
      <Animation0 TYPE="UINT">55030</Animation0>
    </RECORD>
    <RECORD>
      <AnimType KEY="TRUE" TYPE="STR">IdleFidget_Girl_Wand</AnimType>
      <NumAnims TYPE="INT">1</NumAnims>
      <Animation0 TYPE="UINT">3030</Animation0>
    </RECORD>
    <RECORD>
      <AnimType KEY="TRUE" TYPE="STR">IdleFidget_Piggle</AnimType>
      <NumAnims TYPE="INT">1</NumAnims>
      <Animation0 TYPE="UINT">30</Animation0>
    </RECORD>
    <RECORD>
      <AnimType KEY="TRUE" TYPE="STR">IdleFidgetSwim</AnimType>
      <NumAnims TYPE="INT">1</NumAnims>
      <Animation0 TYPE="UINT">32</Animation0>
    </RECORD>
    <RECORD>
      <AnimType KEY="TRUE" TYPE="STR">IdleFidgetSwim_Boy_Relic</AnimType>
      <NumAnims TYPE="INT">1</NumAnims>
      <Animation0 TYPE="UINT">45032</Animation0>
    </RECORD>
    <RECORD>
      <AnimType KEY="TRUE" TYPE="STR">IdleSwim</AnimType>
      <NumAnims TYPE="INT">1</NumAnims>
      <Animation0 TYPE="UINT">22</Animation0>
    </RECORD>
    <RECORD>
      <AnimType KEY="TRUE" TYPE="STR">IdleSwim_Boy_Relic</AnimType>
      <NumAnims TYPE="INT">1</NumAnims>
      <Animation0 TYPE="UINT">45022</Animation0>
    </RECORD>
    <RECORD>
      <AnimType KEY="TRUE" TYPE="STR">Jump</AnimType>
      <NumAnims TYPE="INT">1</NumAnims>
      <Priority TYPE="INT">1</Priority>
      <Animation0 TYPE="UINT">630</Animation0>
    </RECORD>
    <RECORD>
      <AnimType KEY="TRUE" TYPE="STR">Jump_Boy</AnimType>
      <NumAnims TYPE="INT">1</NumAnims>
      <Priority TYPE="INT">1</Priority>
      <Animation0 TYPE="UINT">630</Animation0>
    </RECORD>
    <RECORD>
      <AnimType KEY="TRUE" TYPE="STR">Jump_Boy_Relic</AnimType>
      <NumAnims TYPE="INT">1</NumAnims>
      <Animation0 TYPE="UINT">45630</Animation0>
    </RECORD>
    <RECORD>
      <AnimType KEY="TRUE" TYPE="STR">Jump_Boy_Rifle</AnimType>
      <NumAnims TYPE="INT">1</NumAnims>
      <Animation0 TYPE="UINT">50630</Animation0>
    </RECORD>
    <RECORD>
      <AnimType KEY="TRUE" TYPE="STR">Jump_Boy_Swim_SwordShield</AnimType>
      <NumAnims TYPE="INT">1</NumAnims>
      <Animation0 TYPE="UINT">43635</Animation0>
    </RECORD>
    <RECORD>
      <AnimType KEY="TRUE" TYPE="STR">Jump_Boy_SwordShield</AnimType>
      <NumAnims TYPE="INT">1</NumAnims>
      <Animation0 TYPE="UINT">43630</Animation0>
    </RECORD>
    <RECORD>
      <AnimType KEY="TRUE" TYPE="STR">Jump_Boy_Whip</AnimType>
      <NumAnims TYPE="INT">1</NumAnims>
      <Animation0 TYPE="UINT">56630</Animation0>
    </RECORD>
    <RECORD>
      <AnimType KEY="TRUE" TYPE="STR">Jump_Girl</AnimType>
      <NumAnims TYPE="INT">1</NumAnims>
      <Priority TYPE="INT">1</Priority>
      <Animation0 TYPE="UINT">1630</Animation0>
    </RECORD>
    <RECORD>
      <AnimType KEY="TRUE" TYPE="STR">Jump_Girl_Relic</AnimType>
      <NumAnims TYPE="INT">1</NumAnims>
      <Animation0 TYPE="UINT">45630</Animation0>
    </RECORD>
    <RECORD>
      <AnimType KEY="TRUE" TYPE="STR">JumpSwim</AnimType>
      <NumAnims TYPE="INT">1</NumAnims>
      <Priority TYPE="INT">1</Priority>
      <Animation0 TYPE="UINT">635</Animation0>
    </RECORD>
    <RECORD>
      <AnimType KEY="TRUE" TYPE="STR">JumpSwim_Boy_Relic</AnimType>
      <NumAnims TYPE="INT">1</NumAnims>
      <Animation0 TYPE="UINT">45635</Animation0>
    </RECORD>
    <RECORD>
      <AnimType KEY="TRUE" TYPE="STR">Laugh</AnimType>
      <NumAnims TYPE="INT">1</NumAnims>
      <Animation0 TYPE="UINT">607</Animation0>
    </RECORD>
    <RECORD>
      <AnimType KEY="TRUE" TYPE="STR">LebowskiDance</AnimType>
      <NumAnims TYPE="INT">1</NumAnims>
      <Animation0 TYPE="UINT">589</Animation0>
    </RECORD>
    <RECORD>
      <AnimType KEY="TRUE" TYPE="STR">Miss</AnimType>
      <NumAnims TYPE="INT">1</NumAnims>
      <Animation0 TYPE="UINT">375</Animation0>
    </RECORD>
    <RECORD>
      <AnimType KEY="TRUE" TYPE="STR">MountIdle</AnimType>
      <NumAnims TYPE="INT">1</NumAnims>
      <Animation0 TYPE="UINT">10020</Animation0>
    </RECORD>
    <RECORD>
      <AnimType KEY="TRUE" TYPE="STR">MountIdleFidget</AnimType>
      <NumAnims TYPE="INT">1</NumAnims>
      <Animation0 TYPE="UINT">10030</Animation0>
    </RECORD>
    <RECORD>
      <AnimType KEY="TRUE" TYPE="STR">MountIdleFidgetSwim</AnimType>
      <NumAnims TYPE="INT">1</NumAnims>
      <Animation0 TYPE="UINT">10530</Animation0>
    </RECORD>
    <RECORD>
      <AnimType KEY="TRUE" TYPE="STR">MountIdleSwim</AnimType>
      <NumAnims TYPE="INT">1</NumAnims>
      <Animation0 TYPE="UINT">10520</Animation0>
    </RECORD>
    <RECORD>
      <AnimType KEY="TRUE" TYPE="STR">MountJump</AnimType>
      <NumAnims TYPE="INT">1</NumAnims>
      <Priority TYPE="INT">1</Priority>
      <Animation0 TYPE="UINT">10040</Animation0>
    </RECORD>
    <RECORD>
      <AnimType KEY="TRUE" TYPE="STR">MountJumpSwim</AnimType>
      <NumAnims TYPE="INT">1</NumAnims>
      <Priority TYPE="INT">1</Priority>
      <Animation0 TYPE="UINT">10540</Animation0>
    </RECORD>
    <RECORD>
      <AnimType KEY="TRUE" TYPE="STR">MountRunBackward</AnimType>
      <NumAnims TYPE="INT">1</NumAnims>
      <Animation0 TYPE="UINT">10070</Animation0>
    </RECORD>
    <RECORD>
      <AnimType KEY="TRUE" TYPE="STR">MountRunBackwardSwim</AnimType>
      <NumAnims TYPE="INT">1</NumAnims>
      <Animation0 TYPE="UINT">10570</Animation0>
    </RECORD>
    <RECORD>
      <AnimType KEY="TRUE" TYPE="STR">MountRunForward</AnimType>
      <NumAnims TYPE="INT">1</NumAnims>
      <Animation0 TYPE="UINT">10060</Animation0>
    </RECORD>
    <RECORD>
      <AnimType KEY="TRUE" TYPE="STR">MountRunForwardSwim</AnimType>
      <NumAnims TYPE="INT">1</NumAnims>
      <Animation0 TYPE="UINT">10560</Animation0>
    </RECORD>
    <RECORD>
      <AnimType KEY="TRUE" TYPE="STR">MountTurnLeft</AnimType>
      <NumAnims TYPE="INT">1</NumAnims>
      <Animation0 TYPE="UINT">10045</Animation0>
    </RECORD>
    <RECORD>
      <AnimType KEY="TRUE" TYPE="STR">MountTurnLeftSwim</AnimType>
      <NumAnims TYPE="INT">1</NumAnims>
      <Animation0 TYPE="UINT">10545</Animation0>
    </RECORD>
    <RECORD>
      <AnimType KEY="TRUE" TYPE="STR">MountTurnRight</AnimType>
      <NumAnims TYPE="INT">1</NumAnims>
      <Animation0 TYPE="UINT">10050</Animation0>
    </RECORD>
    <RECORD>
      <AnimType KEY="TRUE" TYPE="STR">MountTurnRightSwim</AnimType>
      <NumAnims TYPE="INT">1</NumAnims>
      <Animation0 TYPE="UINT">10550</Animation0>
    </RECORD>
    <RECORD>
      <AnimType KEY="TRUE" TYPE="STR">MoveSwim_Boy_Relic</AnimType>
      <NumAnims TYPE="INT">1</NumAnims>
      <Animation0 TYPE="UINT">45560</Animation0>
    </RECORD>
    <RECORD>
      <AnimType KEY="TRUE" TYPE="STR">NaturalAttack2</AnimType>
      <NumAnims TYPE="INT">1</NumAnims>
      <Animation0 TYPE="UINT">701</Animation0>
    </RECORD>
    <RECORD>
      <AnimType KEY="TRUE" TYPE="STR">NaturalAttack3</AnimType>
      <NumAnims TYPE="INT">1</NumAnims>
      <Animation0 TYPE="UINT">702</Animation0>
    </RECORD>
    <RECORD>
      <AnimType KEY="TRUE" TYPE="STR">Oppa</AnimType>
      <NumAnims TYPE="INT">1</NumAnims>
      <Animation0 TYPE="UINT">597</Animation0>
    </RECORD>
    <RECORD>
      <AnimType KEY="TRUE" TYPE="STR">P_B_Attack_Fist</AnimType>
      <NumAnims TYPE="INT">1</NumAnims>
      <Animation0 TYPE="UINT">64700</Animation0>
    </RECORD>
    <RECORD>
      <AnimType KEY="TRUE" TYPE="STR">P_B_Attack_PVP_Corporal</AnimType>
      <NumAnims TYPE="INT">1</NumAnims>
      <Animation0 TYPE="UINT">66700</Animation0>
    </RECORD>
    <RECORD>
      <AnimType KEY="TRUE" TYPE="STR">P_B_Attack_StaffShield</AnimType>
      <NumAnims TYPE="INT">1</NumAnims>
      <Animation0 TYPE="UINT">62700</Animation0>
    </RECORD>
    <RECORD>
      <AnimType KEY="TRUE" TYPE="STR">P_B_Cantrip_Cast_01</AnimType>
      <NumAnims TYPE="INT">1</NumAnims>
      <Priority TYPE="INT">2</Priority>
      <Animation0 TYPE="UINT">10000</Animation0>
    </RECORD>
    <RECORD>
      <AnimType KEY="TRUE" TYPE="STR">P_B_Cantrip_Emote_Backflip</AnimType>
      <NumAnims TYPE="INT">1</NumAnims>
      <Priority TYPE="INT">2</Priority>
      <Animation0 TYPE="UINT">10005</Animation0>
    </RECORD>
    <RECORD>
      <AnimType KEY="TRUE" TYPE="STR">P_B_Cantrip_Emote_Floating</AnimType>
      <NumAnims TYPE="INT">1</NumAnims>
      <Priority TYPE="INT">2</Priority>
      <Animation0 TYPE="UINT">10006</Animation0>
    </RECORD>
    <RECORD>
      <AnimType KEY="TRUE" TYPE="STR">P_B_Cantrip_Emote_Reclining</AnimType>
      <NumAnims TYPE="INT">1</NumAnims>
      <Priority TYPE="INT">2</Priority>
      <Animation0 TYPE="UINT">10008</Animation0>
    </RECORD>
    <RECORD>
      <AnimType KEY="TRUE" TYPE="STR">P_B_Cantrip_Emote_Spellbook</AnimType>
      <NumAnims TYPE="INT">1</NumAnims>
      <Priority TYPE="INT">2</Priority>
      <Animation0 TYPE="UINT">10007</Animation0>
    </RECORD>
    <RECORD>
      <AnimType KEY="TRUE" TYPE="STR">P_B_Cast_Fist</AnimType>
      <NumAnims TYPE="INT">1</NumAnims>
      <Animation0 TYPE="UINT">64144</Animation0>
    </RECORD>
    <RECORD>
      <AnimType KEY="TRUE" TYPE="STR">P_B_Cast_Gardening</AnimType>
      <NumAnims TYPE="INT">1</NumAnims>
      <Animation0 TYPE="UINT">145</Animation0>
    </RECORD>
    <RECORD>
      <AnimType KEY="TRUE" TYPE="STR">P_B_Cast_Mask</AnimType>
      <NumAnims TYPE="INT">1</NumAnims>
      <Animation0 TYPE="UINT">58144</Animation0>
    </RECORD>
    <RECORD>
      <AnimType KEY="TRUE" TYPE="STR">P_B_Cast_PVP_Corporal</AnimType>
      <NumAnims TYPE="INT">1</NumAnims>
      <Animation0 TYPE="UINT">66144</Animation0>
    </RECORD>
    <RECORD>
      <AnimType KEY="TRUE" TYPE="STR">P_B_Cast_StaffShield</AnimType>
      <NumAnims TYPE="INT">1</NumAnims>
      <Animation0 TYPE="UINT">62144</Animation0>
    </RECORD>
    <RECORD>
      <AnimType KEY="TRUE" TYPE="STR">P_B_CombatIdle_Fist</AnimType>
      <NumAnims TYPE="INT">1</NumAnims>
      <Animation0 TYPE="UINT">64001</Animation0>
    </RECORD>
    <RECORD>
      <AnimType KEY="TRUE" TYPE="STR">P_B_CombatIdle_StaffShield</AnimType>
      <NumAnims TYPE="INT">1</NumAnims>
      <Animation0 TYPE="UINT">62001</Animation0>
    </RECORD>
    <RECORD>
      <AnimType KEY="TRUE" TYPE="STR">P_B_Dance_BBoy</AnimType>
      <NumAnims TYPE="INT">1</NumAnims>
      <Animation0 TYPE="UINT">637</Animation0>
    </RECORD>
    <RECORD>
      <AnimType KEY="TRUE" TYPE="STR">P_B_Dance_FunkyJive</AnimType>
      <NumAnims TYPE="INT">1</NumAnims>
      <Animation0 TYPE="UINT">628</Animation0>
    </RECORD>
    <RECORD>
      <AnimType KEY="TRUE" TYPE="STR">P_B_Dance_Shuffle</AnimType>
      <NumAnims TYPE="INT">1</NumAnims>
      <Animation0 TYPE="UINT">636</Animation0>
    </RECORD>
    <RECORD>
      <AnimType KEY="TRUE" TYPE="STR">P_B_Death_StaffShield</AnimType>
      <NumAnims TYPE="INT">1</NumAnims>
      <Animation0 TYPE="UINT">62610</Animation0>
    </RECORD>
    <RECORD>
      <AnimType KEY="TRUE" TYPE="STR">P_B_Emote_BrowWipe</AnimType>
      <NumAnims TYPE="INT">1</NumAnims>
      <Animation0 TYPE="UINT">801</Animation0>
    </RECORD>
    <RECORD>
      <AnimType KEY="TRUE" TYPE="STR">P_B_Emote_Clover</AnimType>
      <NumAnims TYPE="INT">1</NumAnims>
      <Animation0 TYPE="UINT">646</Animation0>
    </RECORD>
    <RECORD>
      <AnimType KEY="TRUE" TYPE="STR">P_B_Emote_Dance_BellyDance</AnimType>
      <NumAnims TYPE="INT">1</NumAnims>
      <Animation0 TYPE="UINT">643</Animation0>
    </RECORD>
    <RECORD>
      <AnimType KEY="TRUE" TYPE="STR">P_B_Emote_Dance_Dougie</AnimType>
      <NumAnims TYPE="INT">1</NumAnims>
      <Animation0 TYPE="UINT">642</Animation0>
    </RECORD>
    <RECORD>
      <AnimType KEY="TRUE" TYPE="STR">P_B_Emote_Dance_GStyle_01</AnimType>
      <NumAnims TYPE="INT">1</NumAnims>
      <Animation0 TYPE="UINT">621</Animation0>
    </RECORD>
    <RECORD>
      <AnimType KEY="TRUE" TYPE="STR">P_B_Emote_Dance_SlideDoubleHop</AnimType>
      <NumAnims TYPE="INT">1</NumAnims>
      <Animation0 TYPE="UINT">640</Animation0>
    </RECORD>
    <RECORD>
      <AnimType KEY="TRUE" TYPE="STR">P_B_Emote_Dance_Soul_01</AnimType>
      <NumAnims TYPE="INT">1</NumAnims>
      <Animation0 TYPE="UINT">638</Animation0>
    </RECORD>
    <RECORD>
      <AnimType KEY="TRUE" TYPE="STR">P_B_Emote_Fall</AnimType>
      <NumAnims TYPE="INT">1</NumAnims>
      <Animation0 TYPE="UINT">644</Animation0>
    </RECORD>
    <RECORD>
      <AnimType KEY="TRUE" TYPE="STR">P_B_Emote_FallSOF2021</AnimType>
      <NumAnims TYPE="INT">1</NumAnims>
      <Animation0 TYPE="UINT">649</Animation0>
    </RECORD>
    <RECORD>
      <AnimType KEY="TRUE" TYPE="STR">P_B_Emote_FlagWave_Checker</AnimType>
      <NumAnims TYPE="INT">1</NumAnims>
      <Animation0 TYPE="UINT">648</Animation0>
    </RECORD>
    <RECORD>
      <AnimType KEY="TRUE" TYPE="STR">P_B_Emote_FlagWave_Green</AnimType>
      <NumAnims TYPE="INT">1</NumAnims>
      <Animation0 TYPE="UINT">647</Animation0>
    </RECORD>
    <RECORD>
      <AnimType KEY="TRUE" TYPE="STR">P_B_Emote_Flowerful</AnimType>
      <NumAnims TYPE="INT">1</NumAnims>
      <Animation0 TYPE="UINT">632</Animation0>
    </RECORD>
    <RECORD>
      <AnimType KEY="TRUE" TYPE="STR">P_B_Emote_LandShark</AnimType>
      <NumAnims TYPE="INT">1</NumAnims>
      <Animation0 TYPE="UINT">802</Animation0>
    </RECORD>
    <RECORD>
      <AnimType KEY="TRUE" TYPE="STR">P_B_Emote_OverHere</AnimType>
      <NumAnims TYPE="INT">1</NumAnims>
      <Animation0 TYPE="UINT">639</Animation0>
    </RECORD>
    <RECORD>
      <AnimType KEY="TRUE" TYPE="STR">P_B_Emote_RunningMan</AnimType>
      <NumAnims TYPE="INT">1</NumAnims>
      <Animation0 TYPE="UINT">641</Animation0>
    </RECORD>
    <RECORD>
      <AnimType KEY="TRUE" TYPE="STR">P_B_Emote_Snowball</AnimType>
      <NumAnims TYPE="INT">1</NumAnims>
      <Animation0 TYPE="UINT">627</Animation0>
    </RECORD>
    <RECORD>
      <AnimType KEY="TRUE" TYPE="STR">P_B_Emote_SpellLevelUp</AnimType>
      <NumAnims TYPE="INT">1</NumAnims>
      <Animation0 TYPE="UINT">631</Animation0>
    </RECORD>
    <RECORD>
      <AnimType KEY="TRUE" TYPE="STR">P_B_Emote_Spring</AnimType>
      <NumAnims TYPE="INT">1</NumAnims>
      <Animation0 TYPE="UINT">633</Animation0>
    </RECORD>
    <RECORD>
      <AnimType KEY="TRUE" TYPE="STR">P_B_Emote_SpringSOF2022</AnimType>
      <NumAnims TYPE="INT">1</NumAnims>
      <Animation0 TYPE="UINT">652</Animation0>
    </RECORD>
    <RECORD>
      <AnimType KEY="TRUE" TYPE="STR">P_B_Emote_StrangeCast_Balance</AnimType>
      <NumAnims TYPE="INT">1</NumAnims>
      <Animation0 TYPE="UINT">626</Animation0>
    </RECORD>
    <RECORD>
      <AnimType KEY="TRUE" TYPE="STR">P_B_Emote_StrangeCast_Death</AnimType>
      <NumAnims TYPE="INT">1</NumAnims>
      <Animation0 TYPE="UINT">615</Animation0>
    </RECORD>
    <RECORD>
      <AnimType KEY="TRUE" TYPE="STR">P_B_Emote_StrangeCast_Fire</AnimType>
      <NumAnims TYPE="INT">1</NumAnims>
      <Animation0 TYPE="UINT">616</Animation0>
    </RECORD>
    <RECORD>
      <AnimType KEY="TRUE" TYPE="STR">P_B_Emote_StrangeCast_Ice</AnimType>
      <NumAnims TYPE="INT">1</NumAnims>
      <Animation0 TYPE="UINT">617</Animation0>
    </RECORD>
    <RECORD>
      <AnimType KEY="TRUE" TYPE="STR">P_B_Emote_StrangeCast_Life</AnimType>
      <NumAnims TYPE="INT">1</NumAnims>
      <Animation0 TYPE="UINT">618</Animation0>
    </RECORD>
    <RECORD>
      <AnimType KEY="TRUE" TYPE="STR">P_B_Emote_StrangeCast_Myth</AnimType>
      <NumAnims TYPE="INT">1</NumAnims>
      <Animation0 TYPE="UINT">619</Animation0>
    </RECORD>
    <RECORD>
      <AnimType KEY="TRUE" TYPE="STR">P_B_Emote_StrangeCast_Storm</AnimType>
      <NumAnims TYPE="INT">1</NumAnims>
      <Animation0 TYPE="UINT">625</Animation0>
    </RECORD>
    <RECORD>
      <AnimType KEY="TRUE" TYPE="STR">P_B_Emote_Summer</AnimType>
      <NumAnims TYPE="INT">1</NumAnims>
      <Animation0 TYPE="UINT">803</Animation0>
    </RECORD>
    <RECORD>
      <AnimType KEY="TRUE" TYPE="STR">P_B_Emote_SummerSOF2022</AnimType>
      <NumAnims TYPE="INT">1</NumAnims>
      <Animation0 TYPE="UINT">651</Animation0>
    </RECORD>
    <RECORD>
      <AnimType KEY="TRUE" TYPE="STR">P_B_Emote_Winter</AnimType>
      <NumAnims TYPE="INT">1</NumAnims>
      <Animation0 TYPE="UINT">629</Animation0>
    </RECORD>
    <RECORD>
      <AnimType KEY="TRUE" TYPE="STR">P_B_Emote_WinterShiver</AnimType>
      <NumAnims TYPE="INT">1</NumAnims>
      <Animation0 TYPE="UINT">804</Animation0>
    </RECORD>
    <RECORD>
      <AnimType KEY="TRUE" TYPE="STR">P_B_Emote_WinterSOF2021</AnimType>
      <NumAnims TYPE="INT">1</NumAnims>
      <Animation0 TYPE="UINT">805</Animation0>
    </RECORD>
    <RECORD>
      <AnimType KEY="TRUE" TYPE="STR">P_B_Fidget_StaffShield</AnimType>
      <NumAnims TYPE="INT">1</NumAnims>
      <Animation0 TYPE="UINT">62030</Animation0>
    </RECORD>
    <RECORD>
      <AnimType KEY="TRUE" TYPE="STR">P_B_Fishing_Activate</AnimType>
      <NumAnims TYPE="INT">1</NumAnims>
      <Animation0 TYPE="UINT">770</Animation0>
    </RECORD>
    <RECORD>
      <AnimType KEY="TRUE" TYPE="STR">P_B_Fishing_Casting</AnimType>
      <NumAnims TYPE="INT">1</NumAnims>
      <Animation0 TYPE="UINT">750</Animation0>
    </RECORD>
    <RECORD>
      <AnimType KEY="TRUE" TYPE="STR">P_B_Fishing_Control</AnimType>
      <NumAnims TYPE="INT">1</NumAnims>
      <Animation0 TYPE="UINT">760</Animation0>
    </RECORD>
    <RECORD>
      <AnimType KEY="TRUE" TYPE="STR">P_B_Fishing_Telekenesis</AnimType>
      <NumAnims TYPE="INT">1</NumAnims>
      <Animation0 TYPE="UINT">780</Animation0>
    </RECORD>
    <RECORD>
      <AnimType KEY="TRUE" TYPE="STR">P_B_Idle_Fist</AnimType>
      <NumAnims TYPE="INT">1</NumAnims>
      <Animation0 TYPE="UINT">64020</Animation0>
    </RECORD>
    <RECORD>
      <AnimType KEY="TRUE" TYPE="STR">P_B_Idle_StaffShield</AnimType>
      <NumAnims TYPE="INT">1</NumAnims>
      <Animation0 TYPE="UINT">62020</Animation0>
    </RECORD>
    <RECORD>
      <AnimType KEY="TRUE" TYPE="STR">P_B_IdleFidget_Fist</AnimType>
      <NumAnims TYPE="INT">1</NumAnims>
      <Animation0 TYPE="UINT">64030</Animation0>
    </RECORD>
    <RECORD>
      <AnimType KEY="TRUE" TYPE="STR">P_B_IdleFidget_PVP_Corporal</AnimType>
      <NumAnims TYPE="INT">1</NumAnims>
      <Animation0 TYPE="UINT">66030</Animation0>
    </RECORD>
    <RECORD>
      <AnimType KEY="TRUE" TYPE="STR">P_B_Run_B_StaffShield</AnimType>
      <NumAnims TYPE="INT">1</NumAnims>
      <Animation0 TYPE="UINT">62520</Animation0>
    </RECORD>
    <RECORD>
      <AnimType KEY="TRUE" TYPE="STR">P_B_Run_Fist</AnimType>
      <NumAnims TYPE="INT">1</NumAnims>
      <Animation0 TYPE="UINT">64500</Animation0>
    </RECORD>
    <RECORD>
      <AnimType KEY="TRUE" TYPE="STR">P_B_Run_StaffShield</AnimType>
      <NumAnims TYPE="INT">1</NumAnims>
      <Animation0 TYPE="UINT">62500</Animation0>
    </RECORD>
    <RECORD>
      <AnimType KEY="TRUE" TYPE="STR">P_B_Swim_Idle_Fist</AnimType>
      <NumAnims TYPE="INT">1</NumAnims>
      <Animation0 TYPE="UINT">64022</Animation0>
    </RECORD>
    <RECORD>
      <AnimType KEY="TRUE" TYPE="STR">P_B_Swim_Move_Fist</AnimType>
      <NumAnims TYPE="INT">1</NumAnims>
      <Animation0 TYPE="UINT">64560</Animation0>
    </RECORD>
    <RECORD>
      <AnimType KEY="TRUE" TYPE="STR">P_B_Swim_Turn_L_Fist</AnimType>
      <NumAnims TYPE="INT">1</NumAnims>
      <Animation0 TYPE="UINT">64570</Animation0>
    </RECORD>
    <RECORD>
      <AnimType KEY="TRUE" TYPE="STR">P_B_Swim_Turn_R_Fist</AnimType>
      <NumAnims TYPE="INT">1</NumAnims>
      <Animation0 TYPE="UINT">64575</Animation0>
    </RECORD>
    <RECORD>
      <AnimType KEY="TRUE" TYPE="STR">P_B_Swim_WalkBackward_Fist</AnimType>
      <NumAnims TYPE="INT">1</NumAnims>
      <Animation0 TYPE="UINT">64565</Animation0>
    </RECORD>
    <RECORD>
      <AnimType KEY="TRUE" TYPE="STR">P_B_SwimBackward_StaffShield</AnimType>
      <NumAnims TYPE="INT">1</NumAnims>
      <Animation0 TYPE="UINT">62565</Animation0>
    </RECORD>
    <RECORD>
      <AnimType KEY="TRUE" TYPE="STR">P_B_SwimIdle_StaffShield</AnimType>
      <NumAnims TYPE="INT">1</NumAnims>
      <Animation0 TYPE="UINT">62022</Animation0>
    </RECORD>
    <RECORD>
      <AnimType KEY="TRUE" TYPE="STR">P_B_SwimMove_StaffShield</AnimType>
      <NumAnims TYPE="INT">1</NumAnims>
      <Animation0 TYPE="UINT">62560</Animation0>
    </RECORD>
    <RECORD>
      <AnimType KEY="TRUE" TYPE="STR">P_B_SwimTurnL_StaffShield</AnimType>
      <NumAnims TYPE="INT">1</NumAnims>
      <Animation0 TYPE="UINT">62570</Animation0>
    </RECORD>
    <RECORD>
      <AnimType KEY="TRUE" TYPE="STR">P_B_SwimTurnR_StaffShield</AnimType>
      <NumAnims TYPE="INT">1</NumAnims>
      <Animation0 TYPE="UINT">62575</Animation0>
    </RECORD>
    <RECORD>
      <AnimType KEY="TRUE" TYPE="STR">P_B_TurnL_StaffShield</AnimType>
      <NumAnims TYPE="INT">1</NumAnims>
      <Animation0 TYPE="UINT">62545</Animation0>
    </RECORD>
    <RECORD>
      <AnimType KEY="TRUE" TYPE="STR">P_B_TurnLeft_Fist</AnimType>
      <NumAnims TYPE="INT">1</NumAnims>
      <Animation0 TYPE="UINT">64545</Animation0>
    </RECORD>
    <RECORD>
      <AnimType KEY="TRUE" TYPE="STR">P_B_TurnR_StaffShield</AnimType>
      <NumAnims TYPE="INT">1</NumAnims>
      <Animation0 TYPE="UINT">62550</Animation0>
    </RECORD>
    <RECORD>
      <AnimType KEY="TRUE" TYPE="STR">P_B_TurnRight_Fist</AnimType>
      <NumAnims TYPE="INT">1</NumAnims>
      <Animation0 TYPE="UINT">64550</Animation0>
    </RECORD>
    <RECORD>
      <AnimType KEY="TRUE" TYPE="STR">PiP_Steal</AnimType>
      <NumAnims TYPE="INT">1</NumAnims>
      <Animation0 TYPE="UINT">1000</Animation0>
    </RECORD>
    <RECORD>
      <AnimType KEY="TRUE" TYPE="STR">Playing_Music</AnimType>
      <NumAnims TYPE="INT">1</NumAnims>
      <Animation0 TYPE="UINT">33</Animation0>
    </RECORD>
    <RECORD>
      <AnimType KEY="TRUE" TYPE="STR">PopinDance</AnimType>
      <NumAnims TYPE="INT">1</NumAnims>
      <Animation0 TYPE="UINT">595</Animation0>
    </RECORD>
    <RECORD>
      <AnimType KEY="TRUE" TYPE="STR">PulpFictionDance</AnimType>
      <NumAnims TYPE="INT">1</NumAnims>
      <Animation0 TYPE="UINT">586</Animation0>
    </RECORD>
    <RECORD>
      <AnimType KEY="TRUE" TYPE="STR">Resurrecting</AnimType>
      <NumAnims TYPE="INT">1</NumAnims>
      <Animation0 TYPE="UINT">616</Animation0>
    </RECORD>
    <RECORD>
      <AnimType KEY="TRUE" TYPE="STR">RideIdle</AnimType>
      <NumAnims TYPE="INT">1</NumAnims>
      <Animation0 TYPE="UINT">1</Animation0>
    </RECORD>
    <RECORD>
      <AnimType KEY="TRUE" TYPE="STR">Run</AnimType>
      <NumAnims TYPE="INT">1</NumAnims>
      <Animation0 TYPE="UINT">500</Animation0>
    </RECORD>
    <RECORD>
      <AnimType KEY="TRUE" TYPE="STR">Run_Boy</AnimType>
      <NumAnims TYPE="INT">1</NumAnims>
      <Animation0 TYPE="UINT">6500</Animation0>
    </RECORD>
    <RECORD>
      <AnimType KEY="TRUE" TYPE="STR">Run_Boy_Banner</AnimType>
      <NumAnims TYPE="INT">1</NumAnims>
      <Animation0 TYPE="UINT">41500</Animation0>
    </RECORD>
    <RECORD>
      <AnimType KEY="TRUE" TYPE="STR">Run_Boy_Bow</AnimType>
      <NumAnims TYPE="INT">1</NumAnims>
      <Animation0 TYPE="UINT">35500</Animation0>
    </RECORD>
    <RECORD>
      <AnimType KEY="TRUE" TYPE="STR">Run_Boy_Relic</AnimType>
      <NumAnims TYPE="INT">1</NumAnims>
      <Animation0 TYPE="UINT">45500</Animation0>
    </RECORD>
    <RECORD>
      <AnimType KEY="TRUE" TYPE="STR">Run_Boy_Rifle</AnimType>
      <NumAnims TYPE="INT">1</NumAnims>
      <Animation0 TYPE="UINT">50560</Animation0>
    </RECORD>
    <RECORD>
      <AnimType KEY="TRUE" TYPE="STR">Run_Boy_Spear</AnimType>
      <NumAnims TYPE="INT">1</NumAnims>
      <Animation0 TYPE="UINT">37500</Animation0>
    </RECORD>
    <RECORD>
      <AnimType KEY="TRUE" TYPE="STR">Run_Boy_Staff</AnimType>
      <NumAnims TYPE="INT">1</NumAnims>
      <Animation0 TYPE="UINT">500</Animation0>
    </RECORD>
    <RECORD>
      <AnimType KEY="TRUE" TYPE="STR">Run_Boy_Sword</AnimType>
      <NumAnims TYPE="INT">1</NumAnims>
      <Animation0 TYPE="UINT">500</Animation0>
    </RECORD>
    <RECORD>
      <AnimType KEY="TRUE" TYPE="STR">Run_Boy_Sword_TwoHanded</AnimType>
      <NumAnims TYPE="INT">1</NumAnims>
      <Animation0 TYPE="UINT">24500</Animation0>
    </RECORD>
    <RECORD>
      <AnimType KEY="TRUE" TYPE="STR">Run_Boy_SwordShield</AnimType>
      <NumAnims TYPE="INT">1</NumAnims>
      <Animation0 TYPE="UINT">43500</Animation0>
    </RECORD>
    <RECORD>
      <AnimType KEY="TRUE" TYPE="STR">Run_Boy_Wand</AnimType>
      <NumAnims TYPE="INT">1</NumAnims>
      <Animation0 TYPE="UINT">500</Animation0>
    </RECORD>
    <RECORD>
      <AnimType KEY="TRUE" TYPE="STR">Run_Boy_Whip</AnimType>
      <NumAnims TYPE="INT">1</NumAnims>
      <Animation0 TYPE="UINT">56500</Animation0>
    </RECORD>
    <RECORD>
      <AnimType KEY="TRUE" TYPE="STR">Run_Girl</AnimType>
      <NumAnims TYPE="INT">1</NumAnims>
      <Animation0 TYPE="UINT">7500</Animation0>
    </RECORD>
    <RECORD>
      <AnimType KEY="TRUE" TYPE="STR">Run_Girl_Bow</AnimType>
      <NumAnims TYPE="INT">1</NumAnims>
      <Animation0 TYPE="UINT">1500</Animation0>
    </RECORD>
    <RECORD>
      <AnimType KEY="TRUE" TYPE="STR">Run_Girl_Relic</AnimType>
      <NumAnims TYPE="INT">1</NumAnims>
      <Animation0 TYPE="UINT">46500</Animation0>
    </RECORD>
    <RECORD>
      <AnimType KEY="TRUE" TYPE="STR">Run_Girl_Staff</AnimType>
      <NumAnims TYPE="INT">1</NumAnims>
      <Animation0 TYPE="UINT">1500</Animation0>
    </RECORD>
    <RECORD>
      <AnimType KEY="TRUE" TYPE="STR">Run_Girl_Sword</AnimType>
      <NumAnims TYPE="INT">1</NumAnims>
      <Animation0 TYPE="UINT">1500</Animation0>
    </RECORD>
    <RECORD>
      <AnimType KEY="TRUE" TYPE="STR">Run_Girl_Sword_TwoHanded</AnimType>
      <NumAnims TYPE="INT">1</NumAnims>
      <Animation0 TYPE="UINT">25500</Animation0>
    </RECORD>
    <RECORD>
      <AnimType KEY="TRUE" TYPE="STR">Run_Girl_SwordShield</AnimType>
      <NumAnims TYPE="INT">1</NumAnims>
      <Animation0 TYPE="UINT">44500</Animation0>
    </RECORD>
    <RECORD>
      <AnimType KEY="TRUE" TYPE="STR">Run_Girl_Wand</AnimType>
      <NumAnims TYPE="INT">1</NumAnims>
      <Animation0 TYPE="UINT">1500</Animation0>
    </RECORD>
    <RECORD>
      <AnimType KEY="TRUE" TYPE="STR">RunBack</AnimType>
      <NumAnims TYPE="INT">1</NumAnims>
      <Animation0 TYPE="UINT">520</Animation0>
    </RECORD>
    <RECORD>
      <AnimType KEY="TRUE" TYPE="STR">RunBack_Boy</AnimType>
      <NumAnims TYPE="INT">1</NumAnims>
      <Animation0 TYPE="UINT">520</Animation0>
    </RECORD>
    <RECORD>
      <AnimType KEY="TRUE" TYPE="STR">RunBack_Boy_Banner</AnimType>
      <NumAnims TYPE="INT">1</NumAnims>
      <Animation0 TYPE="UINT">41520</Animation0>
    </RECORD>
    <RECORD>
      <AnimType KEY="TRUE" TYPE="STR">RunBack_Boy_Relic</AnimType>
      <NumAnims TYPE="INT">1</NumAnims>
      <Animation0 TYPE="UINT">45520</Animation0>
    </RECORD>
    <RECORD>
      <AnimType KEY="TRUE" TYPE="STR">RunBack_Boy_Rifle</AnimType>
      <NumAnims TYPE="INT">1</NumAnims>
      <Animation0 TYPE="UINT">50520</Animation0>
    </RECORD>
    <RECORD>
      <AnimType KEY="TRUE" TYPE="STR">RunBack_Boy_Spear</AnimType>
      <NumAnims TYPE="INT">1</NumAnims>
      <Animation0 TYPE="UINT">37520</Animation0>
    </RECORD>
    <RECORD>
      <AnimType KEY="TRUE" TYPE="STR">RunBack_Boy_Sword_TwoHanded</AnimType>
      <NumAnims TYPE="INT">1</NumAnims>
      <Animation0 TYPE="UINT">24520</Animation0>
    </RECORD>
    <RECORD>
      <AnimType KEY="TRUE" TYPE="STR">RunBack_Boy_SwordShield</AnimType>
      <NumAnims TYPE="INT">1</NumAnims>
      <Animation0 TYPE="UINT">43520</Animation0>
    </RECORD>
    <RECORD>
      <AnimType KEY="TRUE" TYPE="STR">RunBack_Boy_Whip</AnimType>
      <NumAnims TYPE="INT">1</NumAnims>
      <Animation0 TYPE="UINT">56520</Animation0>
    </RECORD>
    <RECORD>
      <AnimType KEY="TRUE" TYPE="STR">RunBack_Girl</AnimType>
      <NumAnims TYPE="INT">1</NumAnims>
      <Animation0 TYPE="UINT">1520</Animation0>
    </RECORD>
    <RECORD>
      <AnimType KEY="TRUE" TYPE="STR">RunBack_Girl_Bow</AnimType>
      <NumAnims TYPE="INT">1</NumAnims>
      <Animation0 TYPE="UINT">36520</Animation0>
    </RECORD>
    <RECORD>
      <AnimType KEY="TRUE" TYPE="STR">RunBack_Girl_Relic</AnimType>
      <NumAnims TYPE="INT">1</NumAnims>
      <Animation0 TYPE="UINT">46520</Animation0>
    </RECORD>
    <RECORD>
      <AnimType KEY="TRUE" TYPE="STR">RunBack_Girl_Relic</AnimType>
      <NumAnims TYPE="INT">1</NumAnims>
      <Animation0 TYPE="UINT">46520</Animation0>
    </RECORD>
    <RECORD>
      <AnimType KEY="TRUE" TYPE="STR">RunBack_Girl_Sword_TwoHanded</AnimType>
      <NumAnims TYPE="INT">1</NumAnims>
      <Animation0 TYPE="UINT">25520</Animation0>
    </RECORD>
    <RECORD>
      <AnimType KEY="TRUE" TYPE="STR">RunBackLeft</AnimType>
      <NumAnims TYPE="INT">1</NumAnims>
      <Animation0 TYPE="UINT">530</Animation0>
    </RECORD>
    <RECORD>
      <AnimType KEY="TRUE" TYPE="STR">RunBackRight</AnimType>
      <NumAnims TYPE="INT">1</NumAnims>
      <Animation0 TYPE="UINT">535</Animation0>
    </RECORD>
    <RECORD>
      <AnimType KEY="TRUE" TYPE="STR">RunBackSwim</AnimType>
      <NumAnims TYPE="INT">1</NumAnims>
      <Animation0 TYPE="UINT">565</Animation0>
    </RECORD>
    <RECORD>
      <AnimType KEY="TRUE" TYPE="STR">RunBackSwim_Relic</AnimType>
      <NumAnims TYPE="INT">1</NumAnims>
      <Animation0 TYPE="UINT">45565</Animation0>
    </RECORD>
    <RECORD>
      <AnimType KEY="TRUE" TYPE="STR">RunLeft</AnimType>
      <NumAnims TYPE="INT">1</NumAnims>
      <Animation0 TYPE="UINT">510</Animation0>
    </RECORD>
    <RECORD>
      <AnimType KEY="TRUE" TYPE="STR">RunRight</AnimType>
      <NumAnims TYPE="INT">1</NumAnims>
      <Animation0 TYPE="UINT">515</Animation0>
    </RECORD>
    <RECORD>
      <AnimType KEY="TRUE" TYPE="STR">RunSwim</AnimType>
      <NumAnims TYPE="INT">1</NumAnims>
      <Animation0 TYPE="UINT">560</Animation0>
    </RECORD>
    <RECORD>
      <AnimType KEY="TRUE" TYPE="STR">Salute</AnimType>
      <NumAnims TYPE="INT">1</NumAnims>
      <Animation0 TYPE="UINT">608</Animation0>
    </RECORD>
    <RECORD>
      <AnimType KEY="TRUE" TYPE="STR">Scold</AnimType>
      <NumAnims TYPE="INT">1</NumAnims>
      <Animation0 TYPE="UINT">609</Animation0>
    </RECORD>
    <RECORD>
      <AnimType KEY="TRUE" TYPE="STR">Shrug</AnimType>
      <NumAnims TYPE="INT">1</NumAnims>
      <Animation0 TYPE="UINT">611</Animation0>
    </RECORD>
    <RECORD>
      <AnimType KEY="TRUE" TYPE="STR">SillyPantsDance</AnimType>
      <NumAnims TYPE="INT">1</NumAnims>
      <Animation0 TYPE="UINT">622</Animation0>
    </RECORD>
    <RECORD>
      <AnimType KEY="TRUE" TYPE="STR">SittingIdle</AnimType>
      <NumAnims TYPE="INT">1</NumAnims>
      <Animation0 TYPE="UINT">40</Animation0>
    </RECORD>
    <RECORD>
      <AnimType KEY="TRUE" TYPE="STR">SittingIdleFidget</AnimType>
      <NumAnims TYPE="INT">1</NumAnims>
      <Animation0 TYPE="UINT">50</Animation0>
    </RECORD>
    <RECORD>
      <AnimType KEY="TRUE" TYPE="STR">Sneeze</AnimType>
      <NumAnims TYPE="INT">1</NumAnims>
      <Animation0 TYPE="UINT">612</Animation0>
    </RECORD>
    <RECORD>
      <AnimType KEY="TRUE" TYPE="STR">Spec_Dial_01</AnimType>
      <NumAnims TYPE="INT">1</NumAnims>
      <Animation0 TYPE="UINT">70</Animation0>
    </RECORD>
    <RECORD>
      <AnimType KEY="TRUE" TYPE="STR">Spec_Dial_02</AnimType>
      <NumAnims TYPE="INT">1</NumAnims>
      <Animation0 TYPE="UINT">71</Animation0>
    </RECORD>
    <RECORD>
      <AnimType KEY="TRUE" TYPE="STR">Spec_Dial_03</AnimType>
      <NumAnims TYPE="INT">1</NumAnims>
      <Animation0 TYPE="UINT">72</Animation0>
    </RECORD>
    <RECORD>
      <AnimType KEY="TRUE" TYPE="STR">Spec_Dial_04</AnimType>
      <NumAnims TYPE="INT">1</NumAnims>
      <Animation0 TYPE="UINT">73</Animation0>
    </RECORD>
    <RECORD>
      <AnimType KEY="TRUE" TYPE="STR">Spec_Dial_05</AnimType>
      <NumAnims TYPE="INT">1</NumAnims>
      <Animation0 TYPE="UINT">74</Animation0>
    </RECORD>
    <RECORD>
      <AnimType KEY="TRUE" TYPE="STR">Spec_Dial_06</AnimType>
      <NumAnims TYPE="INT">1</NumAnims>
      <Animation0 TYPE="UINT">75</Animation0>
    </RECORD>
    <RECORD>
      <AnimType KEY="TRUE" TYPE="STR">Spec_Dial_07</AnimType>
      <NumAnims TYPE="INT">1</NumAnims>
      <Animation0 TYPE="UINT">76</Animation0>
    </RECORD>
    <RECORD>
      <AnimType KEY="TRUE" TYPE="STR">Spec_Dial_08</AnimType>
      <NumAnims TYPE="INT">1</NumAnims>
      <Animation0 TYPE="UINT">78</Animation0>
    </RECORD>
    <RECORD>
      <AnimType KEY="TRUE" TYPE="STR">Spec_Walk_Boy</AnimType>
      <NumAnims TYPE="INT">1</NumAnims>
      <Animation0 TYPE="UINT">503</Animation0>
    </RECORD>
    <RECORD>
      <AnimType KEY="TRUE" TYPE="STR">Swim_Idle_Boy_Mask</AnimType>
      <NumAnims TYPE="INT">1</NumAnims>
      <Animation0 TYPE="UINT">58022</Animation0>
    </RECORD>
    <RECORD>
      <AnimType KEY="TRUE" TYPE="STR">Swim_Move_Boy_Whip</AnimType>
      <NumAnims TYPE="INT">1</NumAnims>
      <Animation0 TYPE="UINT">56560</Animation0>
    </RECORD>
    <RECORD>
      <AnimType KEY="TRUE" TYPE="STR">Swoon</AnimType>
      <NumAnims TYPE="INT">1</NumAnims>
      <Animation0 TYPE="UINT">613</Animation0>
    </RECORD>
    <RECORD>
      <AnimType KEY="TRUE" TYPE="STR">TheShootDance</AnimType>
      <NumAnims TYPE="INT">1</NumAnims>
      <Animation0 TYPE="UINT">624</Animation0>
    </RECORD>
    <RECORD>
      <AnimType KEY="TRUE" TYPE="STR">TransformationAttack</AnimType>
      <NumAnims TYPE="INT">1</NumAnims>
      <Animation0 TYPE="UINT">960</Animation0>
    </RECORD>
    <RECORD>
      <AnimType KEY="TRUE" TYPE="STR">TransformationCast</AnimType>
      <NumAnims TYPE="INT">1</NumAnims>
      <Animation0 TYPE="UINT">990</Animation0>
    </RECORD>
    <RECORD>
      <AnimType KEY="TRUE" TYPE="STR">TransformationDeath</AnimType>
      <NumAnims TYPE="INT">1</NumAnims>
      <Animation0 TYPE="UINT">950</Animation0>
    </RECORD>
    <RECORD>
      <AnimType KEY="TRUE" TYPE="STR">TransformationGetHit</AnimType>
      <NumAnims TYPE="INT">1</NumAnims>
      <Animation0 TYPE="UINT">995</Animation0>
    </RECORD>
    <RECORD>
      <AnimType KEY="TRUE" TYPE="STR">TransformationIdle</AnimType>
      <NumAnims TYPE="INT">1</NumAnims>
      <Animation0 TYPE="UINT">20</Animation0>
    </RECORD>
    <RECORD>
      <AnimType KEY="TRUE" TYPE="STR">TransformationIdleFidget</AnimType>
      <NumAnims TYPE="INT">1</NumAnims>
      <Animation0 TYPE="UINT">30</Animation0>
    </RECORD>
    <RECORD>
      <AnimType KEY="TRUE" TYPE="STR">TransformationIdleFidgetSwim</AnimType>
      <NumAnims TYPE="INT">1</NumAnims>
      <Animation0 TYPE="UINT">985</Animation0>
    </RECORD>
    <RECORD>
      <AnimType KEY="TRUE" TYPE="STR">TransformationIdleSwim</AnimType>
      <NumAnims TYPE="INT">1</NumAnims>
      <Animation0 TYPE="UINT">965</Animation0>
    </RECORD>
    <RECORD>
      <AnimType KEY="TRUE" TYPE="STR">TransformationJump</AnimType>
      <NumAnims TYPE="INT">1</NumAnims>
      <Priority TYPE="INT">1</Priority>
      <Animation0 TYPE="UINT">940</Animation0>
    </RECORD>
    <RECORD>
      <AnimType KEY="TRUE" TYPE="STR">TransformationJumpSwim</AnimType>
      <NumAnims TYPE="INT">1</NumAnims>
      <Priority TYPE="INT">1</Priority>
      <Animation0 TYPE="UINT">945</Animation0>
    </RECORD>
    <RECORD>
      <AnimType KEY="TRUE" TYPE="STR">TransformationRun</AnimType>
      <NumAnims TYPE="INT">1</NumAnims>
      <Animation0 TYPE="UINT">900</Animation0>
    </RECORD>
    <RECORD>
      <AnimType KEY="TRUE" TYPE="STR">TransformationRunBack</AnimType>
      <NumAnims TYPE="INT">1</NumAnims>
      <Animation0 TYPE="UINT">910</Animation0>
    </RECORD>
    <RECORD>
      <AnimType KEY="TRUE" TYPE="STR">TransformationRunBackSwim</AnimType>
      <NumAnims TYPE="INT">1</NumAnims>
      <Animation0 TYPE="UINT">915</Animation0>
    </RECORD>
    <RECORD>
      <AnimType KEY="TRUE" TYPE="STR">TransformationRunSwim</AnimType>
      <NumAnims TYPE="INT">1</NumAnims>
      <Animation0 TYPE="UINT">905</Animation0>
    </RECORD>
    <RECORD>
      <AnimType KEY="TRUE" TYPE="STR">TransformationTurnLeft</AnimType>
      <NumAnims TYPE="INT">1</NumAnims>
      <Animation0 TYPE="UINT">920</Animation0>
    </RECORD>
    <RECORD>
      <AnimType KEY="TRUE" TYPE="STR">TransformationTurnLeftSwim</AnimType>
      <NumAnims TYPE="INT">1</NumAnims>
      <Animation0 TYPE="UINT">925</Animation0>
    </RECORD>
    <RECORD>
      <AnimType KEY="TRUE" TYPE="STR">TransformationTurnRight</AnimType>
      <NumAnims TYPE="INT">1</NumAnims>
      <Animation0 TYPE="UINT">930</Animation0>
    </RECORD>
    <RECORD>
      <AnimType KEY="TRUE" TYPE="STR">TransformationTurnRightSwim</AnimType>
      <NumAnims TYPE="INT">1</NumAnims>
      <Animation0 TYPE="UINT">935</Animation0>
    </RECORD>
    <RECORD>
      <AnimType KEY="TRUE" TYPE="STR">Turn_Right_Boy_Mask</AnimType>
      <NumAnims TYPE="INT">1</NumAnims>
      <Animation0 TYPE="UINT">58550</Animation0>
    </RECORD>
    <RECORD>
      <AnimType KEY="TRUE" TYPE="STR">TurnL_Boy_Swim_SwordShield</AnimType>
      <NumAnims TYPE="INT">1</NumAnims>
      <Animation0 TYPE="UINT">43570</Animation0>
    </RECORD>
    <RECORD>
      <AnimType KEY="TRUE" TYPE="STR">TurnL_Boy_SwordShield</AnimType>
      <NumAnims TYPE="INT">1</NumAnims>
      <Animation0 TYPE="UINT">43545</Animation0>
    </RECORD>
    <RECORD>
      <AnimType KEY="TRUE" TYPE="STR">TurnLeft</AnimType>
      <NumAnims TYPE="INT">1</NumAnims>
      <Animation0 TYPE="UINT">545</Animation0>
    </RECORD>
    <RECORD>
      <AnimType KEY="TRUE" TYPE="STR">TurnLeft_Boy</AnimType>
      <NumAnims TYPE="INT">1</NumAnims>
      <Animation0 TYPE="UINT">2545</Animation0>
    </RECORD>
    <RECORD>
      <AnimType KEY="TRUE" TYPE="STR">TurnLeft_Boy_Banner</AnimType>
      <NumAnims TYPE="INT">1</NumAnims>
      <Animation0 TYPE="UINT">41545</Animation0>
    </RECORD>
    <RECORD>
      <AnimType KEY="TRUE" TYPE="STR">TurnLeft_Boy_Bow</AnimType>
      <NumAnims TYPE="INT">1</NumAnims>
      <Animation0 TYPE="UINT">35545</Animation0>
    </RECORD>
    <RECORD>
      <AnimType KEY="TRUE" TYPE="STR">TurnLeft_Boy_Relic</AnimType>
      <NumAnims TYPE="INT">1</NumAnims>
      <Animation0 TYPE="UINT">45545</Animation0>
    </RECORD>
    <RECORD>
      <AnimType KEY="TRUE" TYPE="STR">TurnLeft_Boy_Rifle</AnimType>
      <NumAnims TYPE="INT">1</NumAnims>
      <Animation0 TYPE="UINT">50045</Animation0>
    </RECORD>
    <RECORD>
      <AnimType KEY="TRUE" TYPE="STR">TurnLeft_Boy_Spear</AnimType>
      <NumAnims TYPE="INT">1</NumAnims>
      <Animation0 TYPE="UINT">37545</Animation0>
    </RECORD>
    <RECORD>
      <AnimType KEY="TRUE" TYPE="STR">TurnLeft_Boy_Staff</AnimType>
      <NumAnims TYPE="INT">1</NumAnims>
      <Animation0 TYPE="UINT">545</Animation0>
    </RECORD>
    <RECORD>
      <AnimType KEY="TRUE" TYPE="STR">TurnLeft_Boy_Sword</AnimType>
      <NumAnims TYPE="INT">1</NumAnims>
      <Animation0 TYPE="UINT">2545</Animation0>
    </RECORD>
    <RECORD>
      <AnimType KEY="TRUE" TYPE="STR">TurnLeft_Boy_Sword_TwoHanded</AnimType>
      <NumAnims TYPE="INT">1</NumAnims>
      <Animation0 TYPE="UINT">24545</Animation0>
    </RECORD>
    <RECORD>
      <AnimType KEY="TRUE" TYPE="STR">TurnLeft_Boy_Wand</AnimType>
      <NumAnims TYPE="INT">1</NumAnims>
      <Animation0 TYPE="UINT">2545</Animation0>
    </RECORD>
    <RECORD>
      <AnimType KEY="TRUE" TYPE="STR">TurnLeft_Girl</AnimType>
      <NumAnims TYPE="INT">1</NumAnims>
      <Animation0 TYPE="UINT">3545</Animation0>
    </RECORD>
    <RECORD>
      <AnimType KEY="TRUE" TYPE="STR">TurnLeft_Girl_Relic</AnimType>
      <NumAnims TYPE="INT">1</NumAnims>
      <Animation0 TYPE="UINT">46545</Animation0>
    </RECORD>
    <RECORD>
      <AnimType KEY="TRUE" TYPE="STR">TurnLeft_Girl_Staff</AnimType>
      <NumAnims TYPE="INT">1</NumAnims>
      <Animation0 TYPE="UINT">1545</Animation0>
    </RECORD>
    <RECORD>
      <AnimType KEY="TRUE" TYPE="STR">TurnLeft_Girl_Sword</AnimType>
      <NumAnims TYPE="INT">1</NumAnims>
      <Animation0 TYPE="UINT">3545</Animation0>
    </RECORD>
    <RECORD>
      <AnimType KEY="TRUE" TYPE="STR">TurnLeft_Girl_Sword_TwoHanded</AnimType>
      <NumAnims TYPE="INT">1</NumAnims>
      <Animation0 TYPE="UINT">25545</Animation0>
    </RECORD>
    <RECORD>
      <AnimType KEY="TRUE" TYPE="STR">TurnLeft_Girl_Wand</AnimType>
      <NumAnims TYPE="INT">1</NumAnims>
      <Animation0 TYPE="UINT">3545</Animation0>
    </RECORD>
    <RECORD>
      <AnimType KEY="TRUE" TYPE="STR">TurnLeftSwim</AnimType>
      <NumAnims TYPE="INT">1</NumAnims>
      <Animation0 TYPE="UINT">570</Animation0>
    </RECORD>
    <RECORD>
      <AnimType KEY="TRUE" TYPE="STR">TurnLeftSwim_Boy_Relic</AnimType>
      <NumAnims TYPE="INT">1</NumAnims>
      <Animation0 TYPE="UINT">45570</Animation0>
    </RECORD>
    <RECORD>
      <AnimType KEY="TRUE" TYPE="STR">TurnR_Boy_Swim_SwordShield</AnimType>
      <NumAnims TYPE="INT">1</NumAnims>
      <Animation0 TYPE="UINT">43575</Animation0>
    </RECORD>
    <RECORD>
      <AnimType KEY="TRUE" TYPE="STR">TurnR_Boy_SwordShield</AnimType>
      <NumAnims TYPE="INT">1</NumAnims>
      <Animation0 TYPE="UINT">43550</Animation0>
    </RECORD>
    <RECORD>
      <AnimType KEY="TRUE" TYPE="STR">TurnRight</AnimType>
      <NumAnims TYPE="INT">1</NumAnims>
      <Animation0 TYPE="UINT">550</Animation0>
    </RECORD>
    <RECORD>
      <AnimType KEY="TRUE" TYPE="STR">TurnRight_Boy</AnimType>
      <NumAnims TYPE="INT">1</NumAnims>
      <Animation0 TYPE="UINT">2550</Animation0>
    </RECORD>
    <RECORD>
      <AnimType KEY="TRUE" TYPE="STR">TurnRight_Boy_Banner</AnimType>
      <NumAnims TYPE="INT">1</NumAnims>
      <Animation0 TYPE="UINT">41550</Animation0>
    </RECORD>
    <RECORD>
      <AnimType KEY="TRUE" TYPE="STR">TurnRight_Boy_Bow</AnimType>
      <NumAnims TYPE="INT">1</NumAnims>
      <Animation0 TYPE="UINT">35550</Animation0>
    </RECORD>
    <RECORD>
      <AnimType KEY="TRUE" TYPE="STR">TurnRight_Boy_Relic</AnimType>
      <NumAnims TYPE="INT">1</NumAnims>
      <Animation0 TYPE="UINT">45550</Animation0>
    </RECORD>
    <RECORD>
      <AnimType KEY="TRUE" TYPE="STR">TurnRight_Boy_Rifle</AnimType>
      <NumAnims TYPE="INT">1</NumAnims>
      <Animation0 TYPE="UINT">50050</Animation0>
    </RECORD>
    <RECORD>
      <AnimType KEY="TRUE" TYPE="STR">TurnRight_Boy_Spear</AnimType>
      <NumAnims TYPE="INT">1</NumAnims>
      <Animation0 TYPE="UINT">37550</Animation0>
    </RECORD>
    <RECORD>
      <AnimType KEY="TRUE" TYPE="STR">TurnRight_Boy_Staff</AnimType>
      <NumAnims TYPE="INT">1</NumAnims>
      <Animation0 TYPE="UINT">550</Animation0>
    </RECORD>
    <RECORD>
      <AnimType KEY="TRUE" TYPE="STR">TurnRight_Boy_Sword</AnimType>
      <NumAnims TYPE="INT">1</NumAnims>
      <Animation0 TYPE="UINT">2550</Animation0>
    </RECORD>
    <RECORD>
      <AnimType KEY="TRUE" TYPE="STR">TurnRight_Boy_Sword_TwoHanded</AnimType>
      <NumAnims TYPE="INT">1</NumAnims>
      <Animation0 TYPE="UINT">24550</Animation0>
    </RECORD>
    <RECORD>
      <AnimType KEY="TRUE" TYPE="STR">TurnRight_Boy_Wand</AnimType>
      <NumAnims TYPE="INT">1</NumAnims>
      <Animation0 TYPE="UINT">2550</Animation0>
    </RECORD>
    <RECORD>
      <AnimType KEY="TRUE" TYPE="STR">TurnRight_Girl</AnimType>
      <NumAnims TYPE="INT">1</NumAnims>
      <Animation0 TYPE="UINT">3550</Animation0>
    </RECORD>
    <RECORD>
      <AnimType KEY="TRUE" TYPE="STR">TurnRight_Girl_Relic</AnimType>
      <NumAnims TYPE="INT">1</NumAnims>
      <Animation0 TYPE="UINT">46550</Animation0>
    </RECORD>
    <RECORD>
      <AnimType KEY="TRUE" TYPE="STR">TurnRight_Girl_Staff</AnimType>
      <NumAnims TYPE="INT">1</NumAnims>
      <Animation0 TYPE="UINT">1550</Animation0>
    </RECORD>
    <RECORD>
      <AnimType KEY="TRUE" TYPE="STR">TurnRight_Girl_Sword</AnimType>
      <NumAnims TYPE="INT">1</NumAnims>
      <Animation0 TYPE="UINT">3550</Animation0>
    </RECORD>
    <RECORD>
      <AnimType KEY="TRUE" TYPE="STR">TurnRight_Girl_Sword_TwoHanded</AnimType>
      <NumAnims TYPE="INT">1</NumAnims>
      <Animation0 TYPE="UINT">25550</Animation0>
    </RECORD>
    <RECORD>
      <AnimType KEY="TRUE" TYPE="STR">TurnRight_Girl_Wand</AnimType>
      <NumAnims TYPE="INT">1</NumAnims>
      <Animation0 TYPE="UINT">3550</Animation0>
    </RECORD>
    <RECORD>
      <AnimType KEY="TRUE" TYPE="STR">TurnRightSwim</AnimType>
      <NumAnims TYPE="INT">1</NumAnims>
      <Animation0 TYPE="UINT">575</Animation0>
    </RECORD>
    <RECORD>
      <AnimType KEY="TRUE" TYPE="STR">TurnRightSwim_Boy_Relic</AnimType>
      <NumAnims TYPE="INT">1</NumAnims>
      <Animation0 TYPE="UINT">45575</Animation0>
    </RECORD>
    <RECORD>
      <AnimType KEY="TRUE" TYPE="STR">Walk_Boy</AnimType>
      <NumAnims TYPE="INT">1</NumAnims>
      <Animation0 TYPE="UINT">502</Animation0>
    </RECORD>
    <RECORD>
      <AnimType KEY="TRUE" TYPE="STR">Walk_Boy_Swim_SwordShield</AnimType>
      <NumAnims TYPE="INT">1</NumAnims>
      <Animation0 TYPE="UINT">43560</Animation0>
    </RECORD>
    <RECORD>
      <AnimType KEY="TRUE" TYPE="STR">WalkBack_Boy_Swim_SwordShield</AnimType>
      <NumAnims TYPE="INT">1</NumAnims>
      <Animation0 TYPE="UINT">43565</Animation0>
    </RECORD>
    <RECORD>
      <AnimType KEY="TRUE" TYPE="STR">Wave</AnimType>
      <NumAnims TYPE="INT">1</NumAnims>
      <Animation0 TYPE="UINT">620</Animation0>
    </RECORD>
    <RECORD>
      <AnimType KEY="TRUE" TYPE="STR">WildStallionsDance</AnimType>
      <NumAnims TYPE="INT">1</NumAnims>
      <Animation0 TYPE="UINT">587</Animation0>
    </RECORD>
    <RECORD>
      <AnimType KEY="TRUE" TYPE="STR">P_B_Dance_Hopak</AnimType>
      <NumAnims TYPE="INT">1</NumAnims>
      <Animation0 TYPE="UINT">584</Animation0>
    </RECORD>
  </Animations>
  <SkeletonMovement>
    <RECORD>
      <Name KEY="TRUE" TYPE="STR">Idle</Name>
      <AnimType TYPE="STR">Idle</AnimType>
    </RECORD>
    <RECORD>
      <Name KEY="TRUE" TYPE="STR">RunForward</Name>
      <AnimType TYPE="STR">Run</AnimType>
    </RECORD>
    <RECORD>
      <Name KEY="TRUE" TYPE="STR">RunBackward</Name>
      <AnimType TYPE="STR">RunBack</AnimType>
    </RECORD>
    <RECORD>
      <Name KEY="TRUE" TYPE="STR">TurnLeft</Name>
      <AnimType TYPE="STR">TurnLeft</AnimType>
    </RECORD>
    <RECORD>
      <Name KEY="TRUE" TYPE="STR">TurnRight</Name>
      <AnimType TYPE="STR">TurnRight</AnimType>
    </RECORD>
  </SkeletonMovement>
</MasterAnimationList>